rtl/alu.v
`timescale 1ns / 1ps

module alu #(
    parameter WIDTH = 16
) (
    input  wire [WIDTH-1:0] a,
    input  wire [WIDTH-1:0] b,
    input  wire [3:0]       alu_op,
    output reg  [WIDTH-1:0] result,
    output wire             zero
);

    localparam ALU_ADD = 4'h0;
    localparam ALU_SUB = 4'h1;
    localparam ALU_AND = 4'h2;
    localparam ALU_OR  = 4'h3;
    localparam ALU_XOR = 4'h4;
    localparam ALU_NOT = 4'h5;

    always @(*) begin
        case (alu_op)
            ALU_ADD: result = a + b;
            ALU_SUB: result = a - b;
            ALU_AND: result = a & b;
            ALU_OR:  result = a | b;
            ALU_XOR: result = a ^ b;
            ALU_NOT: result = ~a;
            default: result = {WIDTH{1'b0}};
        endcase
    end

    assign zero = (result == {WIDTH{1'b0}});

endmodule

rtl/register_file.v
`timescale 1ns / 1ps

module register_file #(
    parameter WIDTH = 16,
    parameter ADDR_WIDTH = 3
) (
    input  wire                  clk,
    input  wire                  rst,
    input  wire                  we,
    input  wire [ADDR_WIDTH-1:0] raddr1,
    input  wire [ADDR_WIDTH-1:0] raddr2,
    input  wire [ADDR_WIDTH-1:0] waddr,
    input  wire [WIDTH-1:0]      wdata,
    output wire [WIDTH-1:0]      rdata1,
    output wire [WIDTH-1:0]      rdata2,
    output wire [WIDTH-1:0]      debug_r0,
    output wire [WIDTH-1:0]      debug_r1,
    output wire [WIDTH-1:0]      debug_r2,
    output wire [WIDTH-1:0]      debug_r3,
    output wire [WIDTH-1:0]      debug_r4,
    output wire [WIDTH-1:0]      debug_r5,
    output wire [WIDTH-1:0]      debug_r6,
    output wire [WIDTH-1:0]      debug_r7
);

    reg [WIDTH-1:0] regs [0:7];
    integer i;

    always @(posedge clk or posedge rst) begin
        if (rst) begin
            for (i = 0; i < 8; i = i + 1) begin
                regs[i] <= {WIDTH{1'b0}};
            end
        end else if (we && (waddr != {ADDR_WIDTH{1'b0}})) begin
            regs[waddr] <= wdata;
        end
    end

    assign rdata1 = (raddr1 == {ADDR_WIDTH{1'b0}}) ? {WIDTH{1'b0}} : regs[raddr1];
    assign rdata2 = (raddr2 == {ADDR_WIDTH{1'b0}}) ? {WIDTH{1'b0}} : regs[raddr2];

    assign debug_r0 = {WIDTH{1'b0}};
    assign debug_r1 = regs[1];
    assign debug_r2 = regs[2];
    assign debug_r3 = regs[3];
    assign debug_r4 = regs[4];
    assign debug_r5 = regs[5];
    assign debug_r6 = regs[6];
    assign debug_r7 = regs[7];

endmodule

rtl/control_unit.v
`timescale 1ns / 1ps

module control_unit (
    input  wire       clk,
    input  wire       rst,
    input  wire [3:0] opcode,
    output reg  [2:0] state,
    output reg        ir_write,
    output reg        reg_write,
    output reg        mem_write,
    output reg        pc_write,
    output reg        alu_src_imm,
    output reg        result_src,
    output reg  [1:0] pc_src,
    output reg  [3:0] alu_op
);

    localparam ST_FETCH     = 3'd0;
    localparam ST_DECODE    = 3'd1;
    localparam ST_EXECUTE   = 3'd2;
    localparam ST_MEMORY    = 3'd3;
    localparam ST_WRITEBACK = 3'd4;
    localparam ST_HALT      = 3'd5;

    localparam OP_NOP   = 4'h0;
    localparam OP_ADD   = 4'h1;
    localparam OP_SUB   = 4'h2;
    localparam OP_AND   = 4'h3;
    localparam OP_OR    = 4'h4;
    localparam OP_XOR   = 4'h5;
    localparam OP_NOT   = 4'h6;
    localparam OP_LOAD  = 4'h7;
    localparam OP_STORE = 4'h8;
    localparam OP_JUMP  = 4'h9;
    localparam OP_BEQ   = 4'hA;
    localparam OP_ADDI  = 4'hB;
    localparam OP_HALT  = 4'hF;

    localparam ALU_ADD = 4'h0;
    localparam ALU_SUB = 4'h1;
    localparam ALU_AND = 4'h2;
    localparam ALU_OR  = 4'h3;
    localparam ALU_XOR = 4'h4;
    localparam ALU_NOT = 4'h5;

    localparam PC_INC    = 2'd0;
    localparam PC_BRANCH = 2'd1;
    localparam PC_JUMP   = 2'd2;

    reg [2:0] next_state;

    always @(posedge clk or posedge rst) begin
        if (rst) begin
            state <= ST_FETCH;
        end else begin
            state <= next_state;
        end
    end

    always @(*) begin
        case (state)
            ST_FETCH: begin
                next_state = ST_DECODE;
            end

            ST_DECODE: begin
                if (opcode == OP_HALT) begin
                    next_state = ST_HALT;
                end else begin
                    next_state = ST_EXECUTE;
                end
            end

            ST_EXECUTE: begin
                case (opcode)
                    OP_LOAD,
                    OP_STORE: next_state = ST_MEMORY;

                    OP_ADD,
                    OP_SUB,
                    OP_AND,
                    OP_OR,
                    OP_XOR,
                    OP_NOT,
                    OP_ADDI: next_state = ST_WRITEBACK;

                    OP_NOP,
                    OP_JUMP,
                    OP_BEQ: next_state = ST_FETCH;

                    default: next_state = ST_FETCH;
                endcase
            end

            ST_MEMORY: begin
                if (opcode == OP_LOAD) begin
                    next_state = ST_WRITEBACK;
                end else begin
                    next_state = ST_FETCH;
                end
            end

            ST_WRITEBACK: begin
                next_state = ST_FETCH;
            end

            ST_HALT: begin
                next_state = ST_HALT;
            end

            default: begin
                next_state = ST_FETCH;
            end
        endcase
    end

    always @(*) begin
        ir_write   = 1'b0;
        reg_write  = 1'b0;
        mem_write  = 1'b0;
        pc_write   = 1'b0;
        alu_src_imm = 1'b0;
        result_src = 1'b0;
        pc_src     = PC_INC;
        alu_op     = ALU_ADD;

        case (opcode)
            OP_SUB:  alu_op = ALU_SUB;
            OP_AND:  alu_op = ALU_AND;
            OP_OR:   alu_op = ALU_OR;
            OP_XOR:  alu_op = ALU_XOR;
            OP_NOT:  alu_op = ALU_NOT;
            default: alu_op = ALU_ADD;
        endcase

        case (state)
            ST_FETCH: begin
                ir_write = 1'b1;
            end

            ST_EXECUTE: begin
                if ((opcode == OP_LOAD) || (opcode == OP_STORE) || (opcode == OP_ADDI)) begin
                    alu_src_imm = 1'b1;
                end

                if (opcode == OP_NOP) begin
                    pc_write = 1'b1;
                    pc_src = PC_INC;
                end else if (opcode == OP_JUMP) begin
                    pc_write = 1'b1;
                    pc_src = PC_JUMP;
                end else if (opcode == OP_BEQ) begin
                    pc_write = 1'b1;
                    pc_src = PC_BRANCH;
                end
            end

            ST_MEMORY: begin
                if (opcode == OP_STORE) begin
                    mem_write = 1'b1;
                    pc_write = 1'b1;
                    pc_src = PC_INC;
                end
            end

            ST_WRITEBACK: begin
                if (opcode == OP_LOAD) begin
                    result_src = 1'b1;
                end

                if ((opcode == OP_ADD)  || (opcode == OP_SUB)  ||
                    (opcode == OP_AND)  || (opcode == OP_OR)   ||
                    (opcode == OP_XOR)  || (opcode == OP_NOT)  ||
                    (opcode == OP_LOAD) || (opcode == OP_ADDI)) begin
                    reg_write = 1'b1;
                end

                pc_write = 1'b1;
                pc_src = PC_INC;
            end

            default: begin
            end
        endcase
    end

endmodule

rtl/processor_core.v
`timescale 1ns / 1ps

module processor_core #(
    parameter DATA_WIDTH = 16,
    parameter ADDR_WIDTH = 8,
    parameter IMEM_SIZE = 256,
    parameter DMEM_SIZE = 256
) (
    input  wire                  clk,
    input  wire                  rst,
    output wire                  halted,
    output wire [ADDR_WIDTH-1:0] pc,
    output wire [DATA_WIDTH-1:0] instr,
    output wire [2:0]            state,
    output wire [DATA_WIDTH-1:0] debug_r0,
    output wire [DATA_WIDTH-1:0] debug_r1,
    output wire [DATA_WIDTH-1:0] debug_r2,
    output wire [DATA_WIDTH-1:0] debug_r3,
    output wire [DATA_WIDTH-1:0] debug_r4,
    output wire [DATA_WIDTH-1:0] debug_r5,
    output wire [DATA_WIDTH-1:0] debug_r6,
    output wire [DATA_WIDTH-1:0] debug_r7
);

    localparam ST_EXECUTE = 3'd2;
    localparam ST_MEMORY = 3'd3;
    localparam ST_HALT = 3'd5;

    localparam OP_NOP   = 4'h0;
    localparam OP_LOAD  = 4'h7;
    localparam OP_STORE = 4'h8;
    localparam OP_JUMP  = 4'h9;
    localparam OP_BEQ   = 4'hA;
    localparam OP_HALT  = 4'hF;

    localparam PC_INC    = 2'd0;
    localparam PC_BRANCH = 2'd1;
    localparam PC_JUMP   = 2'd2;

    reg [ADDR_WIDTH-1:0] pc_reg;
    reg [DATA_WIDTH-1:0] instr_reg;
    reg [DATA_WIDTH-1:0] alu_result_reg;
    reg [DATA_WIDTH-1:0] mem_data_reg;

    reg [DATA_WIDTH-1:0] instr_mem [0:IMEM_SIZE-1];
    reg [DATA_WIDTH-1:0] data_mem  [0:DMEM_SIZE-1];

    wire [3:0] opcode;
    wire [2:0] field_11_9;
    wire [2:0] field_8_6;
    wire [2:0] field_5_3;
    wire [DATA_WIDTH-1:0] imm6_ext;

    wire ir_write;
    wire reg_write;
    wire mem_write;
    wire pc_write;
    wire alu_src_imm;
    wire result_src;
    wire [1:0] pc_src;
    wire [3:0] alu_op;

    wire [2:0] rf_raddr1;
    wire [2:0] rf_raddr2;
    wire [2:0] rf_waddr;
    wire [DATA_WIDTH-1:0] rf_rdata1;
    wire [DATA_WIDTH-1:0] rf_rdata2;
    wire [DATA_WIDTH-1:0] rf_wdata;

    wire [DATA_WIDTH-1:0] alu_b;
    wire [DATA_WIDTH-1:0] alu_result;
    wire alu_zero;
    wire branch_equal;

    integer i;

    initial begin
        pc_reg = {ADDR_WIDTH{1'b0}};
        instr_reg = {DATA_WIDTH{1'b0}};
        alu_result_reg = {DATA_WIDTH{1'b0}};
        mem_data_reg = {DATA_WIDTH{1'b0}};

        for (i = 0; i < IMEM_SIZE; i = i + 1) begin
            instr_mem[i] = {DATA_WIDTH{1'b0}};
        end

        for (i = 0; i < DMEM_SIZE; i = i + 1) begin
            data_mem[i] = {DATA_WIDTH{1'b0}};
        end
    end

    assign opcode = instr_reg[15:12];
    assign field_11_9 = instr_reg[11:9];
    assign field_8_6  = instr_reg[8:6];
    assign field_5_3  = instr_reg[5:3];
    assign imm6_ext = {{10{instr_reg[5]}}, instr_reg[5:0]};

    assign rf_raddr1 = (opcode == OP_BEQ) ? field_11_9 : field_8_6;
    assign rf_raddr2 = (opcode == OP_STORE) ? field_11_9 :
                       (opcode == OP_BEQ)   ? field_8_6  : field_5_3;
    assign rf_waddr = field_11_9;
    assign rf_wdata = result_src ? mem_data_reg : alu_result_reg;

    assign alu_b = alu_src_imm ? imm6_ext : rf_rdata2;
    assign branch_equal = (rf_rdata1 == rf_rdata2);

    assign halted = (state == ST_HALT);
    assign pc = pc_reg;
    assign instr = instr_reg;

    control_unit u_control_unit (
        .clk(clk),
        .rst(rst),
        .opcode(opcode),
        .state(state),
        .ir_write(ir_write),
        .reg_write(reg_write),
        .mem_write(mem_write),
        .pc_write(pc_write),
        .alu_src_imm(alu_src_imm),
        .result_src(result_src),
        .pc_src(pc_src),
        .alu_op(alu_op)
    );

    register_file #(
        .WIDTH(DATA_WIDTH),
        .ADDR_WIDTH(3)
    ) u_register_file (
        .clk(clk),
        .rst(rst),
        .we(reg_write),
        .raddr1(rf_raddr1),
        .raddr2(rf_raddr2),
        .waddr(rf_waddr),
        .wdata(rf_wdata),
        .rdata1(rf_rdata1),
        .rdata2(rf_rdata2),
        .debug_r0(debug_r0),
        .debug_r1(debug_r1),
        .debug_r2(debug_r2),
        .debug_r3(debug_r3),
        .debug_r4(debug_r4),
        .debug_r5(debug_r5),
        .debug_r6(debug_r6),
        .debug_r7(debug_r7)
    );

    alu #(
        .WIDTH(DATA_WIDTH)
    ) u_alu (
        .a(rf_rdata1),
        .b(alu_b),
        .alu_op(alu_op),
        .result(alu_result),
        .zero(alu_zero)
    );

    always @(posedge clk or posedge rst) begin
        if (rst) begin
            pc_reg <= {ADDR_WIDTH{1'b0}};
            instr_reg <= {DATA_WIDTH{1'b0}};
            alu_result_reg <= {DATA_WIDTH{1'b0}};
            mem_data_reg <= {DATA_WIDTH{1'b0}};
        end else begin
            if (ir_write) begin
                instr_reg <= instr_mem[pc_reg];
            end

            if (state == ST_EXECUTE) begin
                alu_result_reg <= alu_result;
            end

            if ((state == ST_MEMORY) && (opcode == OP_LOAD)) begin
                mem_data_reg <= data_mem[alu_result_reg[ADDR_WIDTH-1:0]];
            end

            if (mem_write) begin
                data_mem[alu_result_reg[ADDR_WIDTH-1:0]] <= rf_rdata2;
            end

            if (pc_write) begin
                case (pc_src)
                    PC_INC: begin
                        pc_reg <= pc_reg + {{(ADDR_WIDTH-1){1'b0}}, 1'b1};
                    end

                    PC_BRANCH: begin
                        if (branch_equal) begin
                            pc_reg <= pc_reg + imm6_ext[ADDR_WIDTH-1:0];
                        end else begin
                            pc_reg <= pc_reg + {{(ADDR_WIDTH-1){1'b0}}, 1'b1};
                        end
                    end

                    PC_JUMP: begin
                        pc_reg <= instr_reg[ADDR_WIDTH-1:0];
                    end

                    default: begin
                        pc_reg <= pc_reg + {{(ADDR_WIDTH-1){1'b0}}, 1'b1};
                    end
                endcase
            end
        end
    end

endmodule

tb/processor_core_tb.v
`timescale 1ns / 1ps

module processor_core_tb;

    reg clk;
    reg rst;

    wire halted;
    wire [7:0] pc;
    wire [15:0] instr;
    wire [2:0] state;
    wire [15:0] debug_r0;
    wire [15:0] debug_r1;
    wire [15:0] debug_r2;
    wire [15:0] debug_r3;
    wire [15:0] debug_r4;
    wire [15:0] debug_r5;
    wire [15:0] debug_r6;
    wire [15:0] debug_r7;

    integer cycle_count;
    integer errors;
    integer program_last;
    integer mem_addr;
    integer dump_mem_start;
    integer dump_mem_end;
    integer dump_i;
    integer plusarg_found;
    reg [1023:0] waveform_file;
    reg [1023:0] program_file;
    reg [15:0] expected_r0;
    reg [15:0] expected_r1;
    reg [15:0] expected_r2;
    reg [15:0] expected_r3;
    reg [15:0] expected_r4;
    reg [15:0] expected_r5;
    reg [15:0] expected_r6;
    reg [15:0] expected_r7;
    reg [15:0] expected_mem_value;

    processor_core uut (
        .clk(clk),
        .rst(rst),
        .halted(halted),
        .pc(pc),
        .instr(instr),
        .state(state),
        .debug_r0(debug_r0),
        .debug_r1(debug_r1),
        .debug_r2(debug_r2),
        .debug_r3(debug_r3),
        .debug_r4(debug_r4),
        .debug_r5(debug_r5),
        .debug_r6(debug_r6),
        .debug_r7(debug_r7)
    );

    always #5 clk = ~clk;

    task check16;
        input [127:0] name;
        input [15:0] actual;
        input [15:0] expected;
        begin
            if (actual !== expected) begin
                $display("FAIL: %0s actual=0x%04h expected=0x%04h", name, actual, expected);
                errors = errors + 1;
            end else begin
                $display("PASS: %0s = 0x%04h", name, actual);
            end
        end
    endtask

    initial begin
        clk = 1'b0;
        rst = 1'b1;
        cycle_count = 0;
        errors = 0;

        waveform_file = "reports/processor_core_tb.vcd";
        program_file = "programs/test_program.hex";
        program_last = 14;
        expected_r0 = 16'h0000;
        expected_r1 = 16'h0005;
        expected_r2 = 16'h0007;
        expected_r3 = 16'h000C;
        expected_r4 = 16'h000C;
        expected_r5 = 16'h0000;
        expected_r6 = 16'h0007;
        expected_r7 = 16'hFFFA;
        mem_addr = 10;
        expected_mem_value = 16'h000C;
        dump_mem_start = 0;
        dump_mem_end = -1;

        plusarg_found = $value$plusargs("VCD=%s", waveform_file);
        plusarg_found = $value$plusargs("PROGRAM=%s", program_file);
        plusarg_found = $value$plusargs("PROGRAM_LAST=%d", program_last);
        plusarg_found = $value$plusargs("EXPECT_R0=%h", expected_r0);
        plusarg_found = $value$plusargs("EXPECT_R1=%h", expected_r1);
        plusarg_found = $value$plusargs("EXPECT_R2=%h", expected_r2);
        plusarg_found = $value$plusargs("EXPECT_R3=%h", expected_r3);
        plusarg_found = $value$plusargs("EXPECT_R4=%h", expected_r4);
        plusarg_found = $value$plusargs("EXPECT_R5=%h", expected_r5);
        plusarg_found = $value$plusargs("EXPECT_R6=%h", expected_r6);
        plusarg_found = $value$plusargs("EXPECT_R7=%h", expected_r7);
        plusarg_found = $value$plusargs("EXPECT_MEM_ADDR=%d", mem_addr);
        plusarg_found = $value$plusargs("EXPECT_MEM_VALUE=%h", expected_mem_value);
        plusarg_found = $value$plusargs("DUMP_MEM_START=%d", dump_mem_start);
        plusarg_found = $value$plusargs("DUMP_MEM_END=%d", dump_mem_end);

        $dumpfile(waveform_file);
        $dumpvars(0, processor_core_tb);

        $display("Loading program: %0s", program_file);
        $readmemh(program_file, uut.instr_mem, 0, program_last);

        repeat (2) @(posedge clk);
        rst = 1'b0;

        while (!halted && (cycle_count < 600)) begin
            @(posedge clk);
            cycle_count = cycle_count + 1;
        end

        if (!halted) begin
            $display("FAIL: processor did not halt before timeout");
            errors = errors + 1;
        end else begin
            $display("PASS: processor halted after %0d cycles", cycle_count);
        end

        check16("R0", debug_r0, expected_r0);
        check16("R1", debug_r1, expected_r1);
        check16("R2", debug_r2, expected_r2);
        check16("R3", debug_r3, expected_r3);
        check16("R4", debug_r4, expected_r4);
        check16("R5", debug_r5, expected_r5);
        check16("R6", debug_r6, expected_r6);
        check16("R7", debug_r7, expected_r7);
        check16("MEM", uut.data_mem[mem_addr], expected_mem_value);

        if (dump_mem_end >= dump_mem_start) begin
            $display("MEMORY DUMP [%0d..%0d]", dump_mem_start, dump_mem_end);
            for (dump_i = dump_mem_start; dump_i <= dump_mem_end; dump_i = dump_i + 1) begin
                $display("MEM[%0d] = 0x%04h", dump_i, uut.data_mem[dump_i]);
            end
        end

        if (errors == 0) begin
            $display("SIMULATION PASSED");
        end else begin
            $display("SIMULATION FAILED: %0d error(s)", errors);
        end

        $finish;
    end

endmodule

reports/asoiu_runner.vcd
$date
	Fri May 29 22:08:57 2026
$end
$version
	Icarus Verilog
$end
$timescale
	1ps
$end
$scope module processor_core_tb $end
$var wire 16 ! debug_r0 [15:0] $end
$var wire 3 " state [2:0] $end
$var wire 8 # pc [7:0] $end
$var wire 16 $ instr [15:0] $end
$var wire 1 % halted $end
$var wire 16 & debug_r7 [15:0] $end
$var wire 16 ' debug_r6 [15:0] $end
$var wire 16 ( debug_r5 [15:0] $end
$var wire 16 ) debug_r4 [15:0] $end
$var wire 16 * debug_r3 [15:0] $end
$var wire 16 + debug_r2 [15:0] $end
$var wire 16 , debug_r1 [15:0] $end
$var reg 1 - clk $end
$var reg 16 . expected_mem_value [15:0] $end
$var reg 16 / expected_r0 [15:0] $end
$var reg 16 0 expected_r1 [15:0] $end
$var reg 16 1 expected_r2 [15:0] $end
$var reg 16 2 expected_r3 [15:0] $end
$var reg 16 3 expected_r4 [15:0] $end
$var reg 16 4 expected_r5 [15:0] $end
$var reg 16 5 expected_r6 [15:0] $end
$var reg 16 6 expected_r7 [15:0] $end
$var reg 1024 7 program_file [1023:0] $end
$var reg 1 8 rst $end
$var reg 1024 9 waveform_file [1023:0] $end
$var integer 32 : cycle_count [31:0] $end
$var integer 32 ; dump_i [31:0] $end
$var integer 32 < dump_mem_end [31:0] $end
$var integer 32 = dump_mem_start [31:0] $end
$var integer 32 > errors [31:0] $end
$var integer 32 ? mem_addr [31:0] $end
$var integer 32 @ plusarg_found [31:0] $end
$var integer 32 A program_last [31:0] $end
$scope module uut $end
$var wire 1 - clk $end
$var wire 16 B debug_r0 [15:0] $end
$var wire 16 C instr [15:0] $end
$var wire 8 D pc [7:0] $end
$var wire 3 E rf_waddr [2:0] $end
$var wire 1 8 rst $end
$var wire 3 F state [2:0] $end
$var wire 16 G rf_wdata [15:0] $end
$var wire 16 H rf_rdata2 [15:0] $end
$var wire 16 I rf_rdata1 [15:0] $end
$var wire 3 J rf_raddr2 [2:0] $end
$var wire 3 K rf_raddr1 [2:0] $end
$var wire 1 L result_src $end
$var wire 1 M reg_write $end
$var wire 1 N pc_write $end
$var wire 2 O pc_src [1:0] $end
$var wire 4 P opcode [3:0] $end
$var wire 1 Q mem_write $end
$var wire 1 R ir_write $end
$var wire 16 S imm6_ext [15:0] $end
$var wire 1 % halted $end
$var wire 3 T field_8_6 [2:0] $end
$var wire 3 U field_5_3 [2:0] $end
$var wire 3 V field_11_9 [2:0] $end
$var wire 16 W debug_r7 [15:0] $end
$var wire 16 X debug_r6 [15:0] $end
$var wire 16 Y debug_r5 [15:0] $end
$var wire 16 Z debug_r4 [15:0] $end
$var wire 16 [ debug_r3 [15:0] $end
$var wire 16 \ debug_r2 [15:0] $end
$var wire 16 ] debug_r1 [15:0] $end
$var wire 1 ^ branch_equal $end
$var wire 1 _ alu_zero $end
$var wire 1 ` alu_src_imm $end
$var wire 16 a alu_result [15:0] $end
$var wire 4 b alu_op [3:0] $end
$var wire 16 c alu_b [15:0] $end
$var reg 16 d alu_result_reg [15:0] $end
$var reg 16 e instr_reg [15:0] $end
$var reg 16 f mem_data_reg [15:0] $end
$var reg 8 g pc_reg [7:0] $end
$var integer 32 h i [31:0] $end
$scope module u_alu $end
$var wire 16 i b [15:0] $end
$var wire 1 _ zero $end
$var wire 4 j alu_op [3:0] $end
$var wire 16 k a [15:0] $end
$var reg 16 l result [15:0] $end
$upscope $end
$scope module u_control_unit $end
$var wire 1 - clk $end
$var wire 4 m opcode [3:0] $end
$var wire 1 8 rst $end
$var reg 4 n alu_op [3:0] $end
$var reg 1 ` alu_src_imm $end
$var reg 1 R ir_write $end
$var reg 1 Q mem_write $end
$var reg 3 o next_state [2:0] $end
$var reg 2 p pc_src [1:0] $end
$var reg 1 N pc_write $end
$var reg 1 M reg_write $end
$var reg 1 L result_src $end
$var reg 3 q state [2:0] $end
$upscope $end
$scope module u_register_file $end
$var wire 1 - clk $end
$var wire 16 r debug_r0 [15:0] $end
$var wire 16 s debug_r1 [15:0] $end
$var wire 16 t debug_r2 [15:0] $end
$var wire 16 u debug_r3 [15:0] $end
$var wire 16 v debug_r4 [15:0] $end
$var wire 16 w debug_r5 [15:0] $end
$var wire 16 x debug_r6 [15:0] $end
$var wire 16 y debug_r7 [15:0] $end
$var wire 3 z raddr1 [2:0] $end
$var wire 3 { raddr2 [2:0] $end
$var wire 1 8 rst $end
$var wire 3 | waddr [2:0] $end
$var wire 16 } wdata [15:0] $end
$var wire 1 M we $end
$var wire 16 ~ rdata2 [15:0] $end
$var wire 16 !" rdata1 [15:0] $end
$var integer 32 "" i [31:0] $end
$upscope $end
$upscope $end
$scope task check16 $end
$var reg 16 #" actual [15:0] $end
$var reg 16 $" expected [15:0] $end
$var reg 128 %" name [127:0] $end
$upscope $end
$upscope $end
$enddefinitions $end
#0
$dumpvars
bx %"
bx $"
bx #"
b1000 ""
b0 !"
b0 ~
b0 }
b0 |
b0 {
b0 z
b0 y
b0 x
b0 w
b0 v
b0 u
b0 t
b0 s
b0 r
b0 q
b0 p
b1 o
b0 n
b0 m
b0 l
b0 k
b0 j
b0 i
b100000000 h
b0 g
b0 f
b0 e
b0 d
b0 c
b0 b
b0 a
0`
1_
1^
b0 ]
b0 \
b0 [
b0 Z
b0 Y
b0 X
b0 W
b0 V
b0 U
b0 T
b0 S
1R
0Q
b0 P
b0 O
0N
0M
0L
b0 K
b0 J
b0 I
b0 H
b0 G
b0 F
b0 E
b0 D
b0 C
b0 B
b10000 A
b1 @
b1011 ?
b0 >
b0 =
b1111 <
bx ;
b0 :
b11100100110010101110000011011110111001001110100011100110010111101100001011100110110111101101001011101010101111101110010011101010110111001101110011001010111001000101110011101100110001101100100 9
18
b11100110110001101110010011010010111000001110100011100110010111101100110011010010110001001101111011011100110000101100011011000110110100100101110011010000110010101111000 7
b0 6
b0 5
b1100 4
b1011001 3
b0 2
b1011001 1
b110111 0
b0 /
b1011001 .
0-
b0 ,
b0 +
b0 *
b0 )
b0 (
b0 '
b0 &
0%
b0 $
b0 #
b0 "
b0 !
$end
#5000
b1000 ""
1-
#10000
0-
#15000
0R
b10 o
b1011 P
b1011 m
b1 E
b1 |
b1 V
b1 "
b1 F
b1 q
b1011001000000000 $
b1011001000000000 C
b1011001000000000 e
08
1-
#20000
0-
#25000
1`
b100 o
b10 "
b10 F
b10 q
b1 :
1-
#30000
0-
#35000
1N
1M
0`
b0 o
b100 "
b100 F
b100 q
b10 :
1-
#40000
0-
#45000
1R
0N
0M
b1 o
b1 #
b1 D
b1 g
b0 "
b0 F
b0 q
b11 :
1-
#50000
0-
#55000
0R
b10 o
b10 E
b10 |
b10 V
b1 S
b1 "
b1 F
b1 q
b1011010000000001 $
b1011010000000001 C
b1011010000000001 e
b100 :
1-
#60000
0-
#65000
0_
b1 a
b1 l
b1 c
b1 i
1`
b100 o
b10 "
b10 F
b10 q
b101 :
1-
#70000
0-
#75000
1_
b0 a
b0 l
b0 c
b0 i
1N
1M
0`
b0 o
b1 G
b1 }
b100 "
b100 F
b100 q
b1 d
b110 :
1-
#80000
0-
#85000
1R
0N
0M
b1 o
b10 #
b10 D
b10 g
b1 +
b1 \
b1 t
b0 "
b0 F
b0 q
b111 :
1-
#90000
0-
#95000
b1 J
b1 {
0R
b10 o
b11 E
b11 |
b11 V
b1 U
b1010 S
b1 "
b1 F
b1 q
b1011011000001010 $
b1011011000001010 C
b1011011000001010 e
b1000 :
1-
#100000
0-
#105000
0_
b1010 a
b1010 l
b1010 c
b1010 i
1`
b100 o
b10 "
b10 F
b10 q
b1001 :
1-
#110000
0-
#115000
1_
b0 a
b0 l
b0 c
b0 i
1N
1M
0`
b0 o
b1010 G
b1010 }
b100 "
b100 F
b100 q
b1010 d
b1010 :
1-
#120000
0-
#125000
1R
0N
0M
b1 o
b11 #
b11 D
b11 g
b1010 *
b1010 [
b1010 u
b0 "
b0 F
b0 q
b1011 :
1-
#130000
0-
#135000
b0 J
b0 {
0R
b10 o
b101 E
b101 |
b101 V
b0 U
b0 S
b1 "
b1 F
b1 q
b1011101000000000 $
b1011101000000000 C
b1011101000000000 e
b1100 :
1-
#140000
0-
#145000
1`
b100 o
b10 "
b10 F
b10 q
b1101 :
1-
#150000
0-
#155000
1N
1M
0`
b0 o
b0 G
b0 }
b100 "
b100 F
b100 q
b0 d
b1110 :
1-
#160000
0-
#165000
1R
0N
0M
b1 o
b100 #
b100 D
b100 g
b0 "
b0 F
b0 q
b1111 :
1-
#170000
0-
#175000
b1 J
b1 {
b101 K
b101 z
0R
b10 o
b1000 P
b1000 m
b1 E
b1 |
b1 V
b101 T
b1 "
b1 F
b1 q
b1000001101000000 $
b1000001101000000 C
b1000001101000000 e
b10000 :
1-
#180000
0-
#185000
1`
b11 o
b10 "
b10 F
b10 q
b10001 :
1-
#190000
0-
#195000
1N
1Q
0`
b0 o
b11 "
b11 F
b11 q
b10010 :
1-
#200000
0-
#205000
1R
0N
0Q
b1 o
b101 #
b101 D
b101 g
b0 "
b0 F
b0 q
b10011 :
1-
#210000
0-
#215000
b0 J
b0 {
0R
b10 o
b1011 P
b1011 m
b101 E
b101 |
b101 V
b1 S
b1 "
b1 F
b1 q
b1011101101000001 $
b1011101101000001 C
b1011101101000001 e
b10100 :
1-
#220000
0-
#225000
0_
b1 a
b1 l
b1 c
b1 i
1`
b100 o
b10 "
b10 F
b10 q
b10101 :
1-
#230000
0-
#235000
1_
b0 a
b0 l
b0 c
b0 i
1N
1M
0`
b0 o
b1 G
b1 }
b100 "
b100 F
b100 q
b1 d
b10110 :
1-
#240000
0-
#245000
0_
b1 a
b1 l
0^
b1 I
b1 k
b1 !"
1R
0N
0M
b1 o
b110 #
b110 D
b110 g
b1 (
b1 Y
b1 w
b0 "
b0 F
b0 q
b10111 :
1-
#250000
0-
#255000
b10 a
b10 l
b1 c
b1 i
1^
b1 H
b1 ~
b10 J
b10 {
0R
b10 o
b1000 P
b1000 m
b10 E
b10 |
b10 V
b0 S
b1 "
b1 F
b1 q
b1000010101000000 $
b1000010101000000 C
b1000010101000000 e
b11000 :
1-
#260000
0-
#265000
b1 a
b1 l
b0 c
b0 i
1`
b11 o
b10 "
b10 F
b10 q
b11001 :
1-
#270000
0-
#275000
b10 a
b10 l
b1 c
b1 i
1N
1Q
0`
b0 o
b11 "
b11 F
b11 q
b11010 :
1-
#280000
0-
#285000
1R
0N
0Q
b1 o
b111 #
b111 D
b111 g
b0 "
b0 F
b0 q
b11011 :
1-
#290000
0-
#295000
b1 a
b1 l
b0 c
b0 i
0^
b0 H
b0 ~
b0 J
b0 {
0R
b10 o
b1011 P
b1011 m
b101 E
b101 |
b101 V
b1 S
b1 "
b1 F
b1 q
b1011101101000001 $
b1011101101000001 C
b1011101101000001 e
b11100 :
1-
#300000
0-
#305000
b10 a
b10 l
b1 c
b1 i
1`
b100 o
b10 "
b10 F
b10 q
b11101 :
1-
#310000
0-
#315000
b1 a
b1 l
b0 c
b0 i
1N
1M
0`
b0 o
b10 G
b10 }
b100 "
b100 F
b100 q
b10 d
b11110 :
1-
#320000
0-
#325000
b10 a
b10 l
b10 I
b10 k
b10 !"
1R
0N
0M
b1 o
b1000 #
b1000 D
b1000 g
b10 (
b10 Y
b10 w
b0 "
b0 F
b0 q
b11111 :
1-
#330000
0-
#335000
b1 c
b1 i
0_
b1 a
b1 l
b1 H
b1 ~
0^
b0 I
b0 k
b0 !"
b10 J
b10 {
b1 K
b1 z
0R
b10 o
b1 P
b1 m
b100 E
b100 |
b100 V
b1 T
b10 U
b10000 S
b1 "
b1 F
b1 q
b1100001010000 $
b1100001010000 C
b1100001010000 e
b100000 :
1-
#340000
0-
#345000
b100 o
b10 "
b10 F
b10 q
b100001 :
1-
#350000
0-
#355000
1N
1M
b0 o
b1 G
b1 }
b100 "
b100 F
b100 q
b1 d
b100010 :
1-
#360000
0-
#365000
1R
0N
0M
b1 o
b1001 #
b1001 D
b1001 g
b1 )
b1 Z
b1 v
b0 "
b0 F
b0 q
b100011 :
1-
#370000
0-
#375000
b11 a
b11 l
b10 I
b10 k
b10 !"
b100 J
b100 {
b101 K
b101 z
0R
b10 o
b1000 P
b1000 m
b101 T
b0 U
b0 S
b1 "
b1 F
b1 q
b1000100101000000 $
b1000100101000000 C
b1000100101000000 e
b100100 :
1-
#380000
0-
#385000
b10 a
b10 l
b0 c
b0 i
1`
b11 o
b10 "
b10 F
b10 q
b100101 :
1-
#390000
0-
