rtl/alu.v
`timescale 1ns / 1ps

module alu #(
    parameter WIDTH = 16
) (
    input  wire [WIDTH-1:0] a,
    input  wire [WIDTH-1:0] b,
    input  wire [3:0]       alu_op,
    output reg  [WIDTH-1:0] result,
    output wire             zero
);

    localparam ALU_ADD = 4'h0;
    localparam ALU_SUB = 4'h1;
    localparam ALU_AND = 4'h2;
    localparam ALU_OR  = 4'h3;
    localparam ALU_XOR = 4'h4;
    localparam ALU_NOT = 4'h5;

    always @(*) begin
        case (alu_op)
            ALU_ADD: result = a + b;
            ALU_SUB: result = a - b;
            ALU_AND: result = a & b;
            ALU_OR:  result = a | b;
            ALU_XOR: result = a ^ b;
            ALU_NOT: result = ~a;
            default: result = {WIDTH{1'b0}};
        endcase
    end

    assign zero = (result == {WIDTH{1'b0}});

endmodule

rtl/register_file.v
`timescale 1ns / 1ps

module register_file #(
    parameter WIDTH = 16,
    parameter ADDR_WIDTH = 3
) (
    input  wire                  clk,
    input  wire                  rst,
    input  wire                  we,
    input  wire [ADDR_WIDTH-1:0] raddr1,
    input  wire [ADDR_WIDTH-1:0] raddr2,
    input  wire [ADDR_WIDTH-1:0] waddr,
    input  wire [WIDTH-1:0]      wdata,
    output wire [WIDTH-1:0]      rdata1,
    output wire [WIDTH-1:0]      rdata2,
    output wire [WIDTH-1:0]      debug_r0,
    output wire [WIDTH-1:0]      debug_r1,
    output wire [WIDTH-1:0]      debug_r2,
    output wire [WIDTH-1:0]      debug_r3,
    output wire [WIDTH-1:0]      debug_r4,
    output wire [WIDTH-1:0]      debug_r5,
    output wire [WIDTH-1:0]      debug_r6,
    output wire [WIDTH-1:0]      debug_r7
);

    reg [WIDTH-1:0] regs [0:7];
    integer i;

    always @(posedge clk or posedge rst) begin
        if (rst) begin
            for (i = 0; i < 8; i = i + 1) begin
                regs[i] <= {WIDTH{1'b0}};
            end
        end else if (we && (waddr != {ADDR_WIDTH{1'b0}})) begin
            regs[waddr] <= wdata;
        end
    end

    assign rdata1 = (raddr1 == {ADDR_WIDTH{1'b0}}) ? {WIDTH{1'b0}} : regs[raddr1];
    assign rdata2 = (raddr2 == {ADDR_WIDTH{1'b0}}) ? {WIDTH{1'b0}} : regs[raddr2];

    assign debug_r0 = {WIDTH{1'b0}};
    assign debug_r1 = regs[1];
    assign debug_r2 = regs[2];
    assign debug_r3 = regs[3];
    assign debug_r4 = regs[4];
    assign debug_r5 = regs[5];
    assign debug_r6 = regs[6];
    assign debug_r7 = regs[7];

endmodule

rtl/control_unit.v
`timescale 1ns / 1ps

module control_unit (
    input  wire       clk,
    input  wire       rst,
    input  wire [3:0] opcode,
    output reg  [2:0] state,
    output reg        ir_write,
    output reg        reg_write,
    output reg        mem_write,
    output reg        pc_write,
    output reg        alu_src_imm,
    output reg        result_src,
    output reg  [1:0] pc_src,
    output reg  [3:0] alu_op
);

    localparam ST_FETCH     = 3'd0;
    localparam ST_DECODE    = 3'd1;
    localparam ST_EXECUTE   = 3'd2;
    localparam ST_MEMORY    = 3'd3;
    localparam ST_WRITEBACK = 3'd4;
    localparam ST_HALT      = 3'd5;

    localparam OP_NOP   = 4'h0;
    localparam OP_ADD   = 4'h1;
    localparam OP_SUB   = 4'h2;
    localparam OP_AND   = 4'h3;
    localparam OP_OR    = 4'h4;
    localparam OP_XOR   = 4'h5;
    localparam OP_NOT   = 4'h6;
    localparam OP_LOAD  = 4'h7;
    localparam OP_STORE = 4'h8;
    localparam OP_JUMP  = 4'h9;
    localparam OP_BEQ   = 4'hA;
    localparam OP_ADDI  = 4'hB;
    localparam OP_HALT  = 4'hF;

    localparam ALU_ADD = 4'h0;
    localparam ALU_SUB = 4'h1;
    localparam ALU_AND = 4'h2;
    localparam ALU_OR  = 4'h3;
    localparam ALU_XOR = 4'h4;
    localparam ALU_NOT = 4'h5;

    localparam PC_INC    = 2'd0;
    localparam PC_BRANCH = 2'd1;
    localparam PC_JUMP   = 2'd2;

    reg [2:0] next_state;

    always @(posedge clk or posedge rst) begin
        if (rst) begin
            state <= ST_FETCH;
        end else begin
            state <= next_state;
        end
    end

    always @(*) begin
        case (state)
            ST_FETCH: begin
                next_state = ST_DECODE;
            end

            ST_DECODE: begin
                if (opcode == OP_HALT) begin
                    next_state = ST_HALT;
                end else begin
                    next_state = ST_EXECUTE;
                end
            end

            ST_EXECUTE: begin
                case (opcode)
                    OP_LOAD,
                    OP_STORE: next_state = ST_MEMORY;

                    OP_ADD,
                    OP_SUB,
                    OP_AND,
                    OP_OR,
                    OP_XOR,
                    OP_NOT,
                    OP_ADDI: next_state = ST_WRITEBACK;

                    OP_NOP,
                    OP_JUMP,
                    OP_BEQ: next_state = ST_FETCH;

                    default: next_state = ST_FETCH;
                endcase
            end

            ST_MEMORY: begin
                if (opcode == OP_LOAD) begin
                    next_state = ST_WRITEBACK;
                end else begin
                    next_state = ST_FETCH;
                end
            end

            ST_WRITEBACK: begin
                next_state = ST_FETCH;
            end

            ST_HALT: begin
                next_state = ST_HALT;
            end

            default: begin
                next_state = ST_FETCH;
            end
        endcase
    end

    always @(*) begin
        ir_write   = 1'b0;
        reg_write  = 1'b0;
        mem_write  = 1'b0;
        pc_write   = 1'b0;
        alu_src_imm = 1'b0;
        result_src = 1'b0;
        pc_src     = PC_INC;
        alu_op     = ALU_ADD;

        case (opcode)
            OP_SUB:  alu_op = ALU_SUB;
            OP_AND:  alu_op = ALU_AND;
            OP_OR:   alu_op = ALU_OR;
            OP_XOR:  alu_op = ALU_XOR;
            OP_NOT:  alu_op = ALU_NOT;
            default: alu_op = ALU_ADD;
        endcase

        case (state)
            ST_FETCH: begin
                ir_write = 1'b1;
            end

            ST_EXECUTE: begin
                if ((opcode == OP_LOAD) || (opcode == OP_STORE) || (opcode == OP_ADDI)) begin
                    alu_src_imm = 1'b1;
                end

                if (opcode == OP_NOP) begin
                    pc_write = 1'b1;
                    pc_src = PC_INC;
                end else if (opcode == OP_JUMP) begin
                    pc_write = 1'b1;
                    pc_src = PC_JUMP;
                end else if (opcode == OP_BEQ) begin
                    pc_write = 1'b1;
                    pc_src = PC_BRANCH;
                end
            end

            ST_MEMORY: begin
                if (opcode == OP_STORE) begin
                    mem_write = 1'b1;
                    pc_write = 1'b1;
                    pc_src = PC_INC;
                end
            end

            ST_WRITEBACK: begin
                if (opcode == OP_LOAD) begin
                    result_src = 1'b1;
                end

                if ((opcode == OP_ADD)  || (opcode == OP_SUB)  ||
                    (opcode == OP_AND)  || (opcode == OP_OR)   ||
                    (opcode == OP_XOR)  || (opcode == OP_NOT)  ||
                    (opcode == OP_LOAD) || (opcode == OP_ADDI)) begin
                    reg_write = 1'b1;
                end

                pc_write = 1'b1;
                pc_src = PC_INC;
            end

            default: begin
            end
        endcase
    end

endmodule

rtl/processor_core.v
`timescale 1ns / 1ps

module processor_core #(
    parameter DATA_WIDTH = 16,
    parameter ADDR_WIDTH = 8,
    parameter IMEM_SIZE = 256,
    parameter DMEM_SIZE = 256
) (
    input  wire                  clk,
    input  wire                  rst,
    output wire                  halted,
    output wire [ADDR_WIDTH-1:0] pc,
    output wire [DATA_WIDTH-1:0] instr,
    output wire [2:0]            state,
    output wire [DATA_WIDTH-1:0] debug_r0,
    output wire [DATA_WIDTH-1:0] debug_r1,
    output wire [DATA_WIDTH-1:0] debug_r2,
    output wire [DATA_WIDTH-1:0] debug_r3,
    output wire [DATA_WIDTH-1:0] debug_r4,
    output wire [DATA_WIDTH-1:0] debug_r5,
    output wire [DATA_WIDTH-1:0] debug_r6,
    output wire [DATA_WIDTH-1:0] debug_r7
);

    localparam ST_EXECUTE = 3'd2;
    localparam ST_MEMORY = 3'd3;
    localparam ST_HALT = 3'd5;

    localparam OP_NOP   = 4'h0;
    localparam OP_LOAD  = 4'h7;
    localparam OP_STORE = 4'h8;
    localparam OP_JUMP  = 4'h9;
    localparam OP_BEQ   = 4'hA;
    localparam OP_HALT  = 4'hF;

    localparam PC_INC    = 2'd0;
    localparam PC_BRANCH = 2'd1;
    localparam PC_JUMP   = 2'd2;

    reg [ADDR_WIDTH-1:0] pc_reg;
    reg [DATA_WIDTH-1:0] instr_reg;
    reg [DATA_WIDTH-1:0] alu_result_reg;
    reg [DATA_WIDTH-1:0] mem_data_reg;

    reg [DATA_WIDTH-1:0] instr_mem [0:IMEM_SIZE-1];
    reg [DATA_WIDTH-1:0] data_mem  [0:DMEM_SIZE-1];

    wire [3:0] opcode;
    wire [2:0] field_11_9;
    wire [2:0] field_8_6;
    wire [2:0] field_5_3;
    wire [DATA_WIDTH-1:0] imm6_ext;

    wire ir_write;
    wire reg_write;
    wire mem_write;
    wire pc_write;
    wire alu_src_imm;
    wire result_src;
    wire [1:0] pc_src;
    wire [3:0] alu_op;

    wire [2:0] rf_raddr1;
    wire [2:0] rf_raddr2;
    wire [2:0] rf_waddr;
    wire [DATA_WIDTH-1:0] rf_rdata1;
    wire [DATA_WIDTH-1:0] rf_rdata2;
    wire [DATA_WIDTH-1:0] rf_wdata;

    wire [DATA_WIDTH-1:0] alu_b;
    wire [DATA_WIDTH-1:0] alu_result;
    wire alu_zero;
    wire branch_equal;

    integer i;

    initial begin
        pc_reg = {ADDR_WIDTH{1'b0}};
        instr_reg = {DATA_WIDTH{1'b0}};
        alu_result_reg = {DATA_WIDTH{1'b0}};
        mem_data_reg = {DATA_WIDTH{1'b0}};

        for (i = 0; i < IMEM_SIZE; i = i + 1) begin
            instr_mem[i] = {DATA_WIDTH{1'b0}};
        end

        for (i = 0; i < DMEM_SIZE; i = i + 1) begin
            data_mem[i] = {DATA_WIDTH{1'b0}};
        end
    end

    assign opcode = instr_reg[15:12];
    assign field_11_9 = instr_reg[11:9];
    assign field_8_6  = instr_reg[8:6];
    assign field_5_3  = instr_reg[5:3];
    assign imm6_ext = {{10{instr_reg[5]}}, instr_reg[5:0]};

    assign rf_raddr1 = (opcode == OP_BEQ) ? field_11_9 : field_8_6;
    assign rf_raddr2 = (opcode == OP_STORE) ? field_11_9 :
                       (opcode == OP_BEQ)   ? field_8_6  : field_5_3;
    assign rf_waddr = field_11_9;
    assign rf_wdata = result_src ? mem_data_reg : alu_result_reg;

    assign alu_b = alu_src_imm ? imm6_ext : rf_rdata2;
    assign branch_equal = (rf_rdata1 == rf_rdata2);

    assign halted = (state == ST_HALT);
    assign pc = pc_reg;
    assign instr = instr_reg;

    control_unit u_control_unit (
        .clk(clk),
        .rst(rst),
        .opcode(opcode),
        .state(state),
        .ir_write(ir_write),
        .reg_write(reg_write),
        .mem_write(mem_write),
        .pc_write(pc_write),
        .alu_src_imm(alu_src_imm),
        .result_src(result_src),
        .pc_src(pc_src),
        .alu_op(alu_op)
    );

    register_file #(
        .WIDTH(DATA_WIDTH),
        .ADDR_WIDTH(3)
    ) u_register_file (
        .clk(clk),
        .rst(rst),
        .we(reg_write),
        .raddr1(rf_raddr1),
        .raddr2(rf_raddr2),
        .waddr(rf_waddr),
        .wdata(rf_wdata),
        .rdata1(rf_rdata1),
        .rdata2(rf_rdata2),
        .debug_r0(debug_r0),
        .debug_r1(debug_r1),
        .debug_r2(debug_r2),
        .debug_r3(debug_r3),
        .debug_r4(debug_r4),
        .debug_r5(debug_r5),
        .debug_r6(debug_r6),
        .debug_r7(debug_r7)
    );

    alu #(
        .WIDTH(DATA_WIDTH)
    ) u_alu (
        .a(rf_rdata1),
        .b(alu_b),
        .alu_op(alu_op),
        .result(alu_result),
        .zero(alu_zero)
    );

    always @(posedge clk or posedge rst) begin
        if (rst) begin
            pc_reg <= {ADDR_WIDTH{1'b0}};
            instr_reg <= {DATA_WIDTH{1'b0}};
            alu_result_reg <= {DATA_WIDTH{1'b0}};
            mem_data_reg <= {DATA_WIDTH{1'b0}};
        end else begin
            if (ir_write) begin
                instr_reg <= instr_mem[pc_reg];
            end

            if (state == ST_EXECUTE) begin
                alu_result_reg <= alu_result;
            end

            if ((state == ST_MEMORY) && (opcode == OP_LOAD)) begin
                mem_data_reg <= data_mem[alu_result_reg[ADDR_WIDTH-1:0]];
            end

            if (mem_write) begin
                data_mem[alu_result_reg[ADDR_WIDTH-1:0]] <= rf_rdata2;
            end

            if (pc_write) begin
                case (pc_src)
                    PC_INC: begin
                        pc_reg <= pc_reg + {{(ADDR_WIDTH-1){1'b0}}, 1'b1};
                    end

                    PC_BRANCH: begin
                        if (branch_equal) begin
                            pc_reg <= pc_reg + imm6_ext[ADDR_WIDTH-1:0];
                        end else begin
                            pc_reg <= pc_reg + {{(ADDR_WIDTH-1){1'b0}}, 1'b1};
                        end
                    end

                    PC_JUMP: begin
                        pc_reg <= instr_reg[ADDR_WIDTH-1:0];
                    end

                    default: begin
                        pc_reg <= pc_reg + {{(ADDR_WIDTH-1){1'b0}}, 1'b1};
                    end
                endcase
            end
        end
    end

endmodule

tb/processor_core_tb.v
`timescale 1ns / 1ps

module processor_core_tb;

    reg clk;
    reg rst;

    wire halted;
    wire [7:0] pc;
    wire [15:0] instr;
    wire [2:0] state;
    wire [15:0] debug_r0;
    wire [15:0] debug_r1;
    wire [15:0] debug_r2;
    wire [15:0] debug_r3;
    wire [15:0] debug_r4;
    wire [15:0] debug_r5;
    wire [15:0] debug_r6;
    wire [15:0] debug_r7;

    integer cycle_count;
    integer errors;
    integer program_last;
    integer mem_addr;
    reg [1023:0] waveform_file;
    reg [1023:0] program_file;
    reg [15:0] expected_r0;
    reg [15:0] expected_r1;
    reg [15:0] expected_r2;
    reg [15:0] expected_r3;
    reg [15:0] expected_r4;
    reg [15:0] expected_r5;
    reg [15:0] expected_r6;
    reg [15:0] expected_r7;
    reg [15:0] expected_mem_value;

    processor_core uut (
        .clk(clk),
        .rst(rst),
        .halted(halted),
        .pc(pc),
        .instr(instr),
        .state(state),
        .debug_r0(debug_r0),
        .debug_r1(debug_r1),
        .debug_r2(debug_r2),
        .debug_r3(debug_r3),
        .debug_r4(debug_r4),
        .debug_r5(debug_r5),
        .debug_r6(debug_r6),
        .debug_r7(debug_r7)
    );

    always #5 clk = ~clk;

    task check16;
        input [127:0] name;
        input [15:0] actual;
        input [15:0] expected;
        begin
            if (actual !== expected) begin
                $display("FAIL: %0s actual=0x%04h expected=0x%04h", name, actual, expected);
                errors = errors + 1;
            end else begin
                $display("PASS: %0s = 0x%04h", name, actual);
            end
        end
    endtask

    initial begin
        clk = 1'b0;
        rst = 1'b1;
        cycle_count = 0;
        errors = 0;

        waveform_file = "reports/processor_core_tb.vcd";
        program_file = "programs/test_program.hex";
        program_last = 14;
        expected_r0 = 16'h0000;
        expected_r1 = 16'h0005;
        expected_r2 = 16'h0007;
        expected_r3 = 16'h000C;
        expected_r4 = 16'h000C;
        expected_r5 = 16'h0000;
        expected_r6 = 16'h0007;
        expected_r7 = 16'hFFFA;
        mem_addr = 10;
        expected_mem_value = 16'h000C;

        if ($value$plusargs("VCD=%s", waveform_file)) begin
        end
        if ($value$plusargs("PROGRAM=%s", program_file)) begin
        end
        if ($value$plusargs("PROGRAM_LAST=%d", program_last)) begin
        end
        if ($value$plusargs("EXPECT_R0=%h", expected_r0)) begin
        end
        if ($value$plusargs("EXPECT_R1=%h", expected_r1)) begin
        end
        if ($value$plusargs("EXPECT_R2=%h", expected_r2)) begin
        end
        if ($value$plusargs("EXPECT_R3=%h", expected_r3)) begin
        end
        if ($value$plusargs("EXPECT_R4=%h", expected_r4)) begin
        end
        if ($value$plusargs("EXPECT_R5=%h", expected_r5)) begin
        end
        if ($value$plusargs("EXPECT_R6=%h", expected_r6)) begin
        end
        if ($value$plusargs("EXPECT_R7=%h", expected_r7)) begin
        end
        if ($value$plusargs("EXPECT_MEM_ADDR=%d", mem_addr)) begin
        end
        if ($value$plusargs("EXPECT_MEM_VALUE=%h", expected_mem_value)) begin
        end

        $dumpfile(waveform_file);
        $dumpvars(0, processor_core_tb);

        $display("Loading program: %0s", program_file);
        $readmemh(program_file, uut.instr_mem, 0, program_last);

        repeat (2) @(posedge clk);
        rst = 1'b0;

        while (!halted && (cycle_count < 200)) begin
            @(posedge clk);
            cycle_count = cycle_count + 1;
        end

        if (!halted) begin
            $display("FAIL: processor did not halt before timeout");
            errors = errors + 1;
        end else begin
            $display("PASS: processor halted after %0d cycles", cycle_count);
        end

        check16("R0", debug_r0, expected_r0);
        check16("R1", debug_r1, expected_r1);
        check16("R2", debug_r2, expected_r2);
        check16("R3", debug_r3, expected_r3);
        check16("R4", debug_r4, expected_r4);
        check16("R5", debug_r5, expected_r5);
        check16("R6", debug_r6, expected_r6);
        check16("R7", debug_r7, expected_r7);
        check16("MEM", uut.data_mem[mem_addr], expected_mem_value);

        if (errors == 0) begin
            $display("SIMULATION PASSED");
        end else begin
            $display("SIMULATION FAILED: %0d error(s)", errors);
        end

        $finish;
    end

endmodule

reports/processor_core_tb.vcd
$date
	Tue May 19 03:17:45 2026
$end
$version
	Icarus Verilog
$end
$timescale
	1ps
$end
$scope module processor_core_tb $end
$var wire 16 ! debug_r0 [15:0] $end
$var wire 3 " state [2:0] $end
$var wire 8 # pc [7:0] $end
$var wire 16 $ instr [15:0] $end
$var wire 1 % halted $end
$var wire 16 & debug_r7 [15:0] $end
$var wire 16 ' debug_r6 [15:0] $end
$var wire 16 ( debug_r5 [15:0] $end
$var wire 16 ) debug_r4 [15:0] $end
$var wire 16 * debug_r3 [15:0] $end
$var wire 16 + debug_r2 [15:0] $end
$var wire 16 , debug_r1 [15:0] $end
$var reg 1 - clk $end
$var reg 16 . expected_mem_value [15:0] $end
$var reg 16 / expected_r0 [15:0] $end
$var reg 16 0 expected_r1 [15:0] $end
$var reg 16 1 expected_r2 [15:0] $end
$var reg 16 2 expected_r3 [15:0] $end
$var reg 16 3 expected_r4 [15:0] $end
$var reg 16 4 expected_r5 [15:0] $end
$var reg 16 5 expected_r6 [15:0] $end
$var reg 16 6 expected_r7 [15:0] $end
$var reg 1024 7 program_file [1023:0] $end
$var reg 1 8 rst $end
$var reg 1024 9 waveform_file [1023:0] $end
$var integer 32 : cycle_count [31:0] $end
$var integer 32 ; errors [31:0] $end
$var integer 32 < mem_addr [31:0] $end
$var integer 32 = program_last [31:0] $end
$scope module uut $end
$var wire 1 - clk $end
$var wire 16 > debug_r0 [15:0] $end
$var wire 16 ? instr [15:0] $end
$var wire 8 @ pc [7:0] $end
$var wire 3 A rf_waddr [2:0] $end
$var wire 1 8 rst $end
$var wire 3 B state [2:0] $end
$var wire 16 C rf_wdata [15:0] $end
$var wire 16 D rf_rdata2 [15:0] $end
$var wire 16 E rf_rdata1 [15:0] $end
$var wire 3 F rf_raddr2 [2:0] $end
$var wire 3 G rf_raddr1 [2:0] $end
$var wire 1 H result_src $end
$var wire 1 I reg_write $end
$var wire 1 J pc_write $end
$var wire 2 K pc_src [1:0] $end
$var wire 4 L opcode [3:0] $end
$var wire 1 M mem_write $end
$var wire 1 N ir_write $end
$var wire 16 O imm6_ext [15:0] $end
$var wire 1 % halted $end
$var wire 3 P field_8_6 [2:0] $end
$var wire 3 Q field_5_3 [2:0] $end
$var wire 3 R field_11_9 [2:0] $end
$var wire 16 S debug_r7 [15:0] $end
$var wire 16 T debug_r6 [15:0] $end
$var wire 16 U debug_r5 [15:0] $end
$var wire 16 V debug_r4 [15:0] $end
$var wire 16 W debug_r3 [15:0] $end
$var wire 16 X debug_r2 [15:0] $end
$var wire 16 Y debug_r1 [15:0] $end
$var wire 1 Z branch_equal $end
$var wire 1 [ alu_zero $end
$var wire 1 \ alu_src_imm $end
$var wire 16 ] alu_result [15:0] $end
$var wire 4 ^ alu_op [3:0] $end
$var wire 16 _ alu_b [15:0] $end
$var reg 16 ` alu_result_reg [15:0] $end
$var reg 16 a instr_reg [15:0] $end
$var reg 16 b mem_data_reg [15:0] $end
$var reg 8 c pc_reg [7:0] $end
$var integer 32 d i [31:0] $end
$scope module u_alu $end
$var wire 16 e b [15:0] $end
$var wire 1 [ zero $end
$var wire 4 f alu_op [3:0] $end
$var wire 16 g a [15:0] $end
$var reg 16 h result [15:0] $end
$upscope $end
$scope module u_control_unit $end
$var wire 1 - clk $end
$var wire 4 i opcode [3:0] $end
$var wire 1 8 rst $end
$var reg 4 j alu_op [3:0] $end
$var reg 1 \ alu_src_imm $end
$var reg 1 N ir_write $end
$var reg 1 M mem_write $end
$var reg 3 k next_state [2:0] $end
$var reg 2 l pc_src [1:0] $end
$var reg 1 J pc_write $end
$var reg 1 I reg_write $end
$var reg 1 H result_src $end
$var reg 3 m state [2:0] $end
$upscope $end
$scope module u_register_file $end
$var wire 1 - clk $end
$var wire 16 n debug_r0 [15:0] $end
$var wire 16 o debug_r1 [15:0] $end
$var wire 16 p debug_r2 [15:0] $end
$var wire 16 q debug_r3 [15:0] $end
$var wire 16 r debug_r4 [15:0] $end
$var wire 16 s debug_r5 [15:0] $end
$var wire 16 t debug_r6 [15:0] $end
$var wire 16 u debug_r7 [15:0] $end
$var wire 3 v raddr1 [2:0] $end
$var wire 3 w raddr2 [2:0] $end
$var wire 1 8 rst $end
$var wire 3 x waddr [2:0] $end
$var wire 16 y wdata [15:0] $end
$var wire 1 I we $end
$var wire 16 z rdata2 [15:0] $end
$var wire 16 { rdata1 [15:0] $end
$var integer 32 | i [31:0] $end
$upscope $end
$upscope $end
$scope task check16 $end
$var reg 16 } actual [15:0] $end
$var reg 16 ~ expected [15:0] $end
$var reg 128 !" name [127:0] $end
$upscope $end
$upscope $end
$enddefinitions $end
#0
$dumpvars
bx !"
bx ~
bx }
b1000 |
b0 {
b0 z
b0 y
b0 x
b0 w
b0 v
b0 u
b0 t
b0 s
b0 r
b0 q
b0 p
b0 o
b0 n
b0 m
b0 l
b1 k
b0 j
b0 i
b0 h
b0 g
b0 f
b0 e
b100000000 d
b0 c
b0 b
b0 a
b0 `
b0 _
b0 ^
b0 ]
0\
1[
1Z
b0 Y
b0 X
b0 W
b0 V
b0 U
b0 T
b0 S
b0 R
b0 Q
b0 P
b0 O
1N
0M
b0 L
b0 K
0J
0I
0H
b0 G
b0 F
b0 E
b0 D
b0 C
b0 B
b0 A
b0 @
b0 ?
b0 >
b1110 =
b1010 <
b0 ;
b0 :
b111001001100101011100000110111101110010011101000111001100101111011100000111001001101111011000110110010101110011011100110110111101110010010111110110001101101111011100100110010101011111011101000110001000101110011101100110001101100100 9
18
b1110000011100100110111101100111011100100110000101101101011100110010111101110100011001010111001101110100010111110111000001110010011011110110011101110010011000010110110100101110011010000110010101111000 7
b1111111111111010 6
b111 5
b0 4
b1100 3
b1100 2
b111 1
b101 0
b0 /
b1100 .
0-
b0 ,
b0 +
b0 *
b0 )
b0 (
b0 '
b0 &
0%
b0 $
b0 #
b0 "
b0 !
$end
#5000
b1000 |
1-
#10000
0-
#15000
0N
b10 k
b1011 L
b1011 i
b1 A
b1 x
b1 R
b101 O
b1 "
b1 B
b1 m
b1011001000000101 $
b1011001000000101 ?
b1011001000000101 a
08
1-
#20000
0-
#25000
0[
b101 ]
b101 h
b101 _
b101 e
1\
b100 k
b10 "
b10 B
b10 m
b1 :
1-
#30000
0-
#35000
1[
b0 ]
b0 h
b0 _
b0 e
1J
1I
0\
b0 k
b101 C
b101 y
b100 "
b100 B
b100 m
b101 `
b10 :
1-
#40000
0-
#45000
1N
0J
0I
b1 k
b1 #
b1 @
b1 c
b101 ,
b101 Y
b101 o
b0 "
b0 B
b0 m
b11 :
1-
#50000
0-
#55000
0N
b10 k
b10 A
b10 x
b10 R
b111 O
b1 "
b1 B
b1 m
b1011010000000111 $
b1011010000000111 ?
b1011010000000111 a
b100 :
1-
#60000
0-
#65000
0[
b111 ]
b111 h
b111 _
b111 e
1\
b100 k
b10 "
b10 B
b10 m
b101 :
1-
#70000
0-
#75000
1[
b0 ]
b0 h
b0 _
b0 e
1J
1I
0\
b0 k
b111 C
b111 y
b100 "
b100 B
b100 m
b111 `
b110 :
1-
#80000
0-
#85000
1N
0J
0I
b1 k
b10 #
b10 @
b10 c
b111 +
b111 X
b111 p
b0 "
b0 B
b0 m
b111 :
1-
#90000
0-
#95000
b111 _
b111 e
0[
b1100 ]
b1100 h
b111 D
b111 z
0Z
b101 E
b101 g
b101 {
b10 F
b10 w
b1 G
b1 v
0N
b10 k
b1 L
b1 i
b11 A
b11 x
b11 R
b1 P
b10 Q
b10000 O
b1 "
b1 B
b1 m
b1011001010000 $
b1011001010000 ?
b1011001010000 a
b1000 :
1-
#100000
0-
#105000
b100 k
b10 "
b10 B
b10 m
b1001 :
1-
#110000
0-
#115000
1J
1I
b0 k
b1100 C
b1100 y
b100 "
b100 B
b100 m
b1100 `
b1010 :
1-
#120000
0-
#125000
1N
0J
0I
b1 k
b11 #
b11 @
b11 c
b1100 *
b1100 W
b1100 q
b0 "
b0 B
b0 m
b1011 :
1-
#130000
0-
#135000
b101 _
b101 e
b101 D
b101 z
b1100 E
b1100 g
b1100 {
b1 F
b1 w
b111 ]
b111 h
b11 G
b11 v
b1 ^
b1 f
b1 j
0N
b10 k
b10 L
b10 i
b110 A
b110 x
b110 R
b11 P
b1 Q
b1000 O
b1 "
b1 B
b1 m
b10110011001000 $
b10110011001000 ?
b10110011001000 a
b1100 :
1-
#140000
0-
#145000
b1 ^
b1 f
b1 j
b100 k
b10 "
b10 B
b10 m
b1101 :
1-
#150000
0-
#155000
1J
1I
b1 ^
b1 f
b1 j
b0 k
b111 C
b111 y
b100 "
b100 B
b100 m
b111 `
b1110 :
1-
#160000
0-
#165000
1N
b1 ^
b1 f
b1 j
0J
0I
b1 k
b100 #
b100 @
b100 c
b111 '
b111 T
b111 t
b0 "
b0 B
b0 m
b1111 :
1-
#170000
0-
#175000
b111 _
b111 e
b111 D
b111 z
0Z
b101 E
b101 g
b101 {
b10 F
b10 w
b101 ]
b101 h
b1 G
b1 v
b10 ^
b10 f
b10 j
0N
b10 k
b11 L
b11 i
b111 A
b111 x
b111 R
b1 P
b10 Q
b10000 O
b1 "
b1 B
b1 m
b11111001010000 $
b11111001010000 ?
b11111001010000 a
b10000 :
1-
#180000
0-
#185000
b10 ^
b10 f
b10 j
b100 k
b10 "
b10 B
b10 m
b10001 :
1-
#190000
0-
#195000
1J
1I
b10 ^
b10 f
b10 j
b0 k
b101 C
b101 y
b100 "
b100 B
b100 m
b101 `
b10010 :
1-
#200000
0-
#205000
1N
b10 ^
b10 f
b10 j
0J
0I
b1 k
b101 #
b101 @
b101 c
b101 &
b101 S
b101 u
b0 "
b0 B
b0 m
b10011 :
1-
#210000
0-
#215000
b111 ]
b111 h
b11 ^
b11 f
b11 j
0N
b10 k
b100 L
b100 i
b1 "
b1 B
b1 m
b100111001010000 $
b100111001010000 ?
b100111001010000 a
b10100 :
1-
#220000
0-
#225000
b11 ^
b11 f
b11 j
b100 k
b10 "
b10 B
b10 m
b10101 :
1-
#230000
0-
#235000
1J
1I
b11 ^
b11 f
b11 j
b0 k
b111 C
b111 y
b100 "
b100 B
b100 m
b111 `
b10110 :
1-
#240000
0-
#245000
1N
b11 ^
b11 f
b11 j
0J
0I
b1 k
b110 #
b110 @
b110 c
b111 &
b111 S
b111 u
b0 "
b0 B
b0 m
b10111 :
1-
#250000
0-
#255000
b10 ]
b10 h
b100 ^
b100 f
b100 j
0N
b10 k
b101 L
b101 i
b1 "
b1 B
b1 m
b101111001010000 $
b101111001010000 ?
b101111001010000 a
b11000 :
1-
#260000
0-
#265000
b100 ^
b100 f
b100 j
b100 k
b10 "
b10 B
b10 m
b11001 :
1-
#270000
0-
#275000
1J
1I
b100 ^
b100 f
b100 j
b0 k
b10 C
b10 y
b100 "
b100 B
b100 m
b10 `
b11010 :
1-
#280000
0-
#285000
1N
b100 ^
b100 f
b100 j
0J
0I
b1 k
b111 #
b111 @
b111 c
b10 &
b10 S
b10 u
b0 "
b0 B
b0 m
b11011 :
1-
#290000
0-
#295000
b0 _
b0 e
b0 D
b0 z
b0 F
b0 w
b1111111111111010 ]
b1111111111111010 h
b101 ^
b101 f
b101 j
0N
b10 k
b110 L
b110 i
b0 Q
b0 O
b1 "
b1 B
b1 m
b110111001000000 $
b110111001000000 ?
b110111001000000 a
b11100 :
1-
#300000
0-
#305000
b101 ^
b101 f
b101 j
b100 k
b10 "
b10 B
b10 m
b11101 :
1-
#310000
0-
#315000
1J
1I
b101 ^
b101 f
b101 j
b0 k
b1111111111111010 C
b1111111111111010 y
b100 "
b100 B
b100 m
b1111111111111010 `
b11110 :
1-
#320000
0-
#325000
1N
b101 ^
b101 f
b101 j
0J
0I
b1 k
b1000 #
b1000 @
b1000 c
b1111111111111010 &
b1111111111111010 S
b1111111111111010 u
b0 "
b0 B
b0 m
b11111 :
1-
#330000
0-
#335000
b1100 _
b1100 e
0[
b1100 D
b1100 z
0Z
b0 E
b0 g
b0 {
b1100 ]
b1100 h
b11 F
b11 w
b0 G
b0 v
b0 ^
b0 f
b0 j
0N
b10 k
b1000 L
b1000 i
b11 A
b11 x
b11 R
b0 P
b1 Q
b1010 O
b1 "
b1 B
b1 m
b1000011000001010 $
b1000011000001010 ?
b1000011000001010 a
b100000 :
1-
#340000
0-
#345000
b1010 ]
b1010 h
b1010 _
b1010 e
1\
b11 k
b10 "
b10 B
b10 m
b100001 :
1-
#350000
0-
#355000
b1100 ]
b1100 h
b1100 _
b1100 e
1J
1M
0\
b0 k
b1010 C
b1010 y
b11 "
b11 B
b11 m
b1010 `
b100010 :
1-
#360000
0-
#365000
1N
0J
0M
b1 k
b1001 #
b1001 @
b1001 c
b0 "
b0 B
b0 m
b100011 :
1-
#370000
0-
#375000
b101 ]
b101 h
b101 _
b101 e
b101 D
b101 z
b1 F
b1 w
0N
b10 k
b111 L
b111 i
b100 A
b100 x
b100 R
b1 "
b1 B
b1 m
b111100000001010 $
b111100000001010 ?
b111100000001010 a
b100100 :
1-
#380000
0-
