rtl/alu.v
`timescale 1ns / 1ps

module alu #(
    parameter WIDTH = 16
) (
    input  wire [WIDTH-1:0] a,
    input  wire [WIDTH-1:0] b,
    input  wire [3:0]       alu_op,
    output reg  [WIDTH-1:0] result,
    output wire             zero
);

    localparam ALU_ADD = 4'h0;
    localparam ALU_SUB = 4'h1;
    localparam ALU_AND = 4'h2;
    localparam ALU_OR  = 4'h3;
    localparam ALU_XOR = 4'h4;
    localparam ALU_NOT = 4'h5;

    always @(*) begin
        case (alu_op)
            ALU_ADD: result = a + b;
            ALU_SUB: result = a - b;
            ALU_AND: result = a & b;
            ALU_OR:  result = a | b;
            ALU_XOR: result = a ^ b;
            ALU_NOT: result = ~a;
            default: result = {WIDTH{1'b0}};
        endcase
    end

    assign zero = (result == {WIDTH{1'b0}});

endmodule

rtl/register_file.v
`timescale 1ns / 1ps

module register_file #(
    parameter WIDTH = 16,
    parameter ADDR_WIDTH = 3
) (
    input  wire                  clk,
    input  wire                  rst,
    input  wire                  we,
    input  wire [ADDR_WIDTH-1:0] raddr1,
    input  wire [ADDR_WIDTH-1:0] raddr2,
    input  wire [ADDR_WIDTH-1:0] waddr,
    input  wire [WIDTH-1:0]      wdata,
    output wire [WIDTH-1:0]      rdata1,
    output wire [WIDTH-1:0]      rdata2,
    output wire [WIDTH-1:0]      debug_r0,
    output wire [WIDTH-1:0]      debug_r1,
    output wire [WIDTH-1:0]      debug_r2,
    output wire [WIDTH-1:0]      debug_r3,
    output wire [WIDTH-1:0]      debug_r4,
    output wire [WIDTH-1:0]      debug_r5,
    output wire [WIDTH-1:0]      debug_r6,
    output wire [WIDTH-1:0]      debug_r7
);

    reg [WIDTH-1:0] regs [0:7];
    integer i;

    always @(posedge clk or posedge rst) begin
        if (rst) begin
            for (i = 0; i < 8; i = i + 1) begin
                regs[i] <= {WIDTH{1'b0}};
            end
        end else if (we && (waddr != {ADDR_WIDTH{1'b0}})) begin
            regs[waddr] <= wdata;
        end
    end

    assign rdata1 = (raddr1 == {ADDR_WIDTH{1'b0}}) ? {WIDTH{1'b0}} : regs[raddr1];
    assign rdata2 = (raddr2 == {ADDR_WIDTH{1'b0}}) ? {WIDTH{1'b0}} : regs[raddr2];

    assign debug_r0 = {WIDTH{1'b0}};
    assign debug_r1 = regs[1];
    assign debug_r2 = regs[2];
    assign debug_r3 = regs[3];
    assign debug_r4 = regs[4];
    assign debug_r5 = regs[5];
    assign debug_r6 = regs[6];
    assign debug_r7 = regs[7];

endmodule

rtl/control_unit.v
`timescale 1ns / 1ps

module control_unit (
    input  wire       clk,
    input  wire       rst,
    input  wire [3:0] opcode,
    output reg  [2:0] state,
    output reg        ir_write,
    output reg        reg_write,
    output reg        mem_write,
    output reg        pc_write,
    output reg        alu_src_imm,
    output reg        result_src,
    output reg  [1:0] pc_src,
    output reg  [3:0] alu_op
);

    localparam ST_FETCH     = 3'd0;
    localparam ST_DECODE    = 3'd1;
    localparam ST_EXECUTE   = 3'd2;
    localparam ST_MEMORY    = 3'd3;
    localparam ST_WRITEBACK = 3'd4;
    localparam ST_HALT      = 3'd5;

    localparam OP_NOP   = 4'h0;
    localparam OP_ADD   = 4'h1;
    localparam OP_SUB   = 4'h2;
    localparam OP_AND   = 4'h3;
    localparam OP_OR    = 4'h4;
    localparam OP_XOR   = 4'h5;
    localparam OP_NOT   = 4'h6;
    localparam OP_LOAD  = 4'h7;
    localparam OP_STORE = 4'h8;
    localparam OP_JUMP  = 4'h9;
    localparam OP_BEQ   = 4'hA;
    localparam OP_ADDI  = 4'hB;
    localparam OP_HALT  = 4'hF;

    localparam ALU_ADD = 4'h0;
    localparam ALU_SUB = 4'h1;
    localparam ALU_AND = 4'h2;
    localparam ALU_OR  = 4'h3;
    localparam ALU_XOR = 4'h4;
    localparam ALU_NOT = 4'h5;

    localparam PC_INC    = 2'd0;
    localparam PC_BRANCH = 2'd1;
    localparam PC_JUMP   = 2'd2;

    reg [2:0] next_state;

    always @(posedge clk or posedge rst) begin
        if (rst) begin
            state <= ST_FETCH;
        end else begin
            state <= next_state;
        end
    end

    always @(*) begin
        case (state)
            ST_FETCH: begin
                next_state = ST_DECODE;
            end

            ST_DECODE: begin
                if (opcode == OP_HALT) begin
                    next_state = ST_HALT;
                end else begin
                    next_state = ST_EXECUTE;
                end
            end

            ST_EXECUTE: begin
                case (opcode)
                    OP_LOAD,
                    OP_STORE: next_state = ST_MEMORY;

                    OP_ADD,
                    OP_SUB,
                    OP_AND,
                    OP_OR,
                    OP_XOR,
                    OP_NOT,
                    OP_ADDI: next_state = ST_WRITEBACK;

                    OP_NOP,
                    OP_JUMP,
                    OP_BEQ: next_state = ST_FETCH;

                    default: next_state = ST_FETCH;
                endcase
            end

            ST_MEMORY: begin
                if (opcode == OP_LOAD) begin
                    next_state = ST_WRITEBACK;
                end else begin
                    next_state = ST_FETCH;
                end
            end

            ST_WRITEBACK: begin
                next_state = ST_FETCH;
            end

            ST_HALT: begin
                next_state = ST_HALT;
            end

            default: begin
                next_state = ST_FETCH;
            end
        endcase
    end

    always @(*) begin
        ir_write   = 1'b0;
        reg_write  = 1'b0;
        mem_write  = 1'b0;
        pc_write   = 1'b0;
        alu_src_imm = 1'b0;
        result_src = 1'b0;
        pc_src     = PC_INC;
        alu_op     = ALU_ADD;

        case (opcode)
            OP_SUB:  alu_op = ALU_SUB;
            OP_AND:  alu_op = ALU_AND;
            OP_OR:   alu_op = ALU_OR;
            OP_XOR:  alu_op = ALU_XOR;
            OP_NOT:  alu_op = ALU_NOT;
            default: alu_op = ALU_ADD;
        endcase

        case (state)
            ST_FETCH: begin
                ir_write = 1'b1;
            end

            ST_EXECUTE: begin
                if ((opcode == OP_LOAD) || (opcode == OP_STORE) || (opcode == OP_ADDI)) begin
                    alu_src_imm = 1'b1;
                end

                if (opcode == OP_NOP) begin
                    pc_write = 1'b1;
                    pc_src = PC_INC;
                end else if (opcode == OP_JUMP) begin
                    pc_write = 1'b1;
                    pc_src = PC_JUMP;
                end else if (opcode == OP_BEQ) begin
                    pc_write = 1'b1;
                    pc_src = PC_BRANCH;
                end
            end

            ST_MEMORY: begin
                if (opcode == OP_STORE) begin
                    mem_write = 1'b1;
                    pc_write = 1'b1;
                    pc_src = PC_INC;
                end
            end

            ST_WRITEBACK: begin
                if (opcode == OP_LOAD) begin
                    result_src = 1'b1;
                end

                if ((opcode == OP_ADD)  || (opcode == OP_SUB)  ||
                    (opcode == OP_AND)  || (opcode == OP_OR)   ||
                    (opcode == OP_XOR)  || (opcode == OP_NOT)  ||
                    (opcode == OP_LOAD) || (opcode == OP_ADDI)) begin
                    reg_write = 1'b1;
                end

                pc_write = 1'b1;
                pc_src = PC_INC;
            end

            default: begin
            end
        endcase
    end

endmodule

rtl/processor_core.v
`timescale 1ns / 1ps

module processor_core #(
    parameter DATA_WIDTH = 16,
    parameter ADDR_WIDTH = 8,
    parameter IMEM_SIZE = 256,
    parameter DMEM_SIZE = 256
) (
    input  wire                  clk,
    input  wire                  rst,
    output wire                  halted,
    output wire [ADDR_WIDTH-1:0] pc,
    output wire [DATA_WIDTH-1:0] instr,
    output wire [2:0]            state,
    output wire [DATA_WIDTH-1:0] debug_r0,
    output wire [DATA_WIDTH-1:0] debug_r1,
    output wire [DATA_WIDTH-1:0] debug_r2,
    output wire [DATA_WIDTH-1:0] debug_r3,
    output wire [DATA_WIDTH-1:0] debug_r4,
    output wire [DATA_WIDTH-1:0] debug_r5,
    output wire [DATA_WIDTH-1:0] debug_r6,
    output wire [DATA_WIDTH-1:0] debug_r7
);

    localparam ST_EXECUTE = 3'd2;
    localparam ST_MEMORY = 3'd3;
    localparam ST_HALT = 3'd5;

    localparam OP_NOP   = 4'h0;
    localparam OP_LOAD  = 4'h7;
    localparam OP_STORE = 4'h8;
    localparam OP_JUMP  = 4'h9;
    localparam OP_BEQ   = 4'hA;
    localparam OP_HALT  = 4'hF;

    localparam PC_INC    = 2'd0;
    localparam PC_BRANCH = 2'd1;
    localparam PC_JUMP   = 2'd2;

    reg [ADDR_WIDTH-1:0] pc_reg;
    reg [DATA_WIDTH-1:0] instr_reg;
    reg [DATA_WIDTH-1:0] alu_result_reg;
    reg [DATA_WIDTH-1:0] mem_data_reg;

    reg [DATA_WIDTH-1:0] instr_mem [0:IMEM_SIZE-1];
    reg [DATA_WIDTH-1:0] data_mem  [0:DMEM_SIZE-1];

    wire [3:0] opcode;
    wire [2:0] field_11_9;
    wire [2:0] field_8_6;
    wire [2:0] field_5_3;
    wire [DATA_WIDTH-1:0] imm6_ext;

    wire ir_write;
    wire reg_write;
    wire mem_write;
    wire pc_write;
    wire alu_src_imm;
    wire result_src;
    wire [1:0] pc_src;
    wire [3:0] alu_op;

    wire [2:0] rf_raddr1;
    wire [2:0] rf_raddr2;
    wire [2:0] rf_waddr;
    wire [DATA_WIDTH-1:0] rf_rdata1;
    wire [DATA_WIDTH-1:0] rf_rdata2;
    wire [DATA_WIDTH-1:0] rf_wdata;

    wire [DATA_WIDTH-1:0] alu_b;
    wire [DATA_WIDTH-1:0] alu_result;
    wire alu_zero;
    wire branch_equal;

    integer i;

    initial begin
        pc_reg = {ADDR_WIDTH{1'b0}};
        instr_reg = {DATA_WIDTH{1'b0}};
        alu_result_reg = {DATA_WIDTH{1'b0}};
        mem_data_reg = {DATA_WIDTH{1'b0}};

        for (i = 0; i < IMEM_SIZE; i = i + 1) begin
            instr_mem[i] = {DATA_WIDTH{1'b0}};
        end

        for (i = 0; i < DMEM_SIZE; i = i + 1) begin
            data_mem[i] = {DATA_WIDTH{1'b0}};
        end
    end

    assign opcode = instr_reg[15:12];
    assign field_11_9 = instr_reg[11:9];
    assign field_8_6  = instr_reg[8:6];
    assign field_5_3  = instr_reg[5:3];
    assign imm6_ext = {{10{instr_reg[5]}}, instr_reg[5:0]};

    assign rf_raddr1 = (opcode == OP_BEQ) ? field_11_9 : field_8_6;
    assign rf_raddr2 = (opcode == OP_STORE) ? field_11_9 :
                       (opcode == OP_BEQ)   ? field_8_6  : field_5_3;
    assign rf_waddr = field_11_9;
    assign rf_wdata = result_src ? mem_data_reg : alu_result_reg;

    assign alu_b = alu_src_imm ? imm6_ext : rf_rdata2;
    assign branch_equal = (rf_rdata1 == rf_rdata2);

    assign halted = (state == ST_HALT);
    assign pc = pc_reg;
    assign instr = instr_reg;

    control_unit u_control_unit (
        .clk(clk),
        .rst(rst),
        .opcode(opcode),
        .state(state),
        .ir_write(ir_write),
        .reg_write(reg_write),
        .mem_write(mem_write),
        .pc_write(pc_write),
        .alu_src_imm(alu_src_imm),
        .result_src(result_src),
        .pc_src(pc_src),
        .alu_op(alu_op)
    );

    register_file #(
        .WIDTH(DATA_WIDTH),
        .ADDR_WIDTH(3)
    ) u_register_file (
        .clk(clk),
        .rst(rst),
        .we(reg_write),
        .raddr1(rf_raddr1),
        .raddr2(rf_raddr2),
        .waddr(rf_waddr),
        .wdata(rf_wdata),
        .rdata1(rf_rdata1),
        .rdata2(rf_rdata2),
        .debug_r0(debug_r0),
        .debug_r1(debug_r1),
        .debug_r2(debug_r2),
        .debug_r3(debug_r3),
        .debug_r4(debug_r4),
        .debug_r5(debug_r5),
        .debug_r6(debug_r6),
        .debug_r7(debug_r7)
    );

    alu #(
        .WIDTH(DATA_WIDTH)
    ) u_alu (
        .a(rf_rdata1),
        .b(alu_b),
        .alu_op(alu_op),
        .result(alu_result),
        .zero(alu_zero)
    );

    always @(posedge clk or posedge rst) begin
        if (rst) begin
            pc_reg <= {ADDR_WIDTH{1'b0}};
            instr_reg <= {DATA_WIDTH{1'b0}};
            alu_result_reg <= {DATA_WIDTH{1'b0}};
            mem_data_reg <= {DATA_WIDTH{1'b0}};
        end else begin
            if (ir_write) begin
                instr_reg <= instr_mem[pc_reg];
            end

            if (state == ST_EXECUTE) begin
                alu_result_reg <= alu_result;
            end

            if ((state == ST_MEMORY) && (opcode == OP_LOAD)) begin
                mem_data_reg <= data_mem[alu_result_reg[ADDR_WIDTH-1:0]];
            end

            if (mem_write) begin
                data_mem[alu_result_reg[ADDR_WIDTH-1:0]] <= rf_rdata2;
            end

            if (pc_write) begin
                case (pc_src)
                    PC_INC: begin
                        pc_reg <= pc_reg + {{(ADDR_WIDTH-1){1'b0}}, 1'b1};
                    end

                    PC_BRANCH: begin
                        if (branch_equal) begin
                            pc_reg <= pc_reg + imm6_ext[ADDR_WIDTH-1:0];
                        end else begin
                            pc_reg <= pc_reg + {{(ADDR_WIDTH-1){1'b0}}, 1'b1};
                        end
                    end

                    PC_JUMP: begin
                        pc_reg <= instr_reg[ADDR_WIDTH-1:0];
                    end

                    default: begin
                        pc_reg <= pc_reg + {{(ADDR_WIDTH-1){1'b0}}, 1'b1};
                    end
                endcase
            end
        end
    end

endmodule

tb/processor_core_tb.v
`timescale 1ns / 1ps

module processor_core_tb;

    reg clk;
    reg rst;

    wire halted;
    wire [7:0] pc;
    wire [15:0] instr;
    wire [2:0] state;
    wire [15:0] debug_r0;
    wire [15:0] debug_r1;
    wire [15:0] debug_r2;
    wire [15:0] debug_r3;
    wire [15:0] debug_r4;
    wire [15:0] debug_r5;
    wire [15:0] debug_r6;
    wire [15:0] debug_r7;

    integer cycle_count;
    integer errors;

    processor_core uut (
        .clk(clk),
        .rst(rst),
        .halted(halted),
        .pc(pc),
        .instr(instr),
        .state(state),
        .debug_r0(debug_r0),
        .debug_r1(debug_r1),
        .debug_r2(debug_r2),
        .debug_r3(debug_r3),
        .debug_r4(debug_r4),
        .debug_r5(debug_r5),
        .debug_r6(debug_r6),
        .debug_r7(debug_r7)
    );

    always #5 clk = ~clk;

    task check16;
        input [127:0] name;
        input [15:0] actual;
        input [15:0] expected;
        begin
            if (actual !== expected) begin
                $display("FAIL: %0s actual=0x%04h expected=0x%04h", name, actual, expected);
                errors = errors + 1;
            end else begin
                $display("PASS: %0s = 0x%04h", name, actual);
            end
        end
    endtask

    initial begin
        $dumpfile("reports/processor_core_tb.vcd");
        $dumpvars(0, processor_core_tb);

        clk = 1'b0;
        rst = 1'b1;
        cycle_count = 0;
        errors = 0;

        $readmemh("programs/test_program.hex", uut.instr_mem, 0, 14);

        repeat (2) @(posedge clk);
        rst = 1'b0;

        while (!halted && (cycle_count < 200)) begin
            @(posedge clk);
            cycle_count = cycle_count + 1;
        end

        if (!halted) begin
            $display("FAIL: processor did not halt before timeout");
            errors = errors + 1;
        end else begin
            $display("PASS: processor halted after %0d cycles", cycle_count);
        end

        check16("R0", debug_r0, 16'd0);
        check16("R1", debug_r1, 16'd5);
        check16("R2", debug_r2, 16'd7);
        check16("R3", debug_r3, 16'd12);
        check16("R4", debug_r4, 16'd12);
        check16("R5", debug_r5, 16'd0);
        check16("R6", debug_r6, 16'd7);
        check16("R7", debug_r7, 16'hFFFA);
        check16("MEM[10]", uut.data_mem[10], 16'd12);

        if (errors == 0) begin
            $display("SIMULATION PASSED");
        end else begin
            $display("SIMULATION FAILED: %0d error(s)", errors);
        end

        $finish;
    end

endmodule

reports/processor_core_tb.vcd
$date
	Tue May 19 01:11:01 2026
$end
$version
	Icarus Verilog
$end
$timescale
	1ps
$end
$scope module processor_core_tb $end
$var wire 16 ! debug_r0 [15:0] $end
$var wire 3 " state [2:0] $end
$var wire 8 # pc [7:0] $end
$var wire 16 $ instr [15:0] $end
$var wire 1 % halted $end
$var wire 16 & debug_r7 [15:0] $end
$var wire 16 ' debug_r6 [15:0] $end
$var wire 16 ( debug_r5 [15:0] $end
$var wire 16 ) debug_r4 [15:0] $end
$var wire 16 * debug_r3 [15:0] $end
$var wire 16 + debug_r2 [15:0] $end
$var wire 16 , debug_r1 [15:0] $end
$var reg 1 - clk $end
$var reg 1 . rst $end
$var integer 32 / cycle_count [31:0] $end
$var integer 32 0 errors [31:0] $end
$scope module uut $end
$var wire 1 - clk $end
$var wire 16 1 debug_r0 [15:0] $end
$var wire 16 2 instr [15:0] $end
$var wire 8 3 pc [7:0] $end
$var wire 3 4 rf_waddr [2:0] $end
$var wire 1 . rst $end
$var wire 3 5 state [2:0] $end
$var wire 16 6 rf_wdata [15:0] $end
$var wire 16 7 rf_rdata2 [15:0] $end
$var wire 16 8 rf_rdata1 [15:0] $end
$var wire 3 9 rf_raddr2 [2:0] $end
$var wire 3 : rf_raddr1 [2:0] $end
$var wire 1 ; result_src $end
$var wire 1 < reg_write $end
$var wire 1 = pc_write $end
$var wire 2 > pc_src [1:0] $end
$var wire 4 ? opcode [3:0] $end
$var wire 1 @ mem_write $end
$var wire 1 A ir_write $end
$var wire 16 B imm6_ext [15:0] $end
$var wire 1 % halted $end
$var wire 3 C field_8_6 [2:0] $end
$var wire 3 D field_5_3 [2:0] $end
$var wire 3 E field_11_9 [2:0] $end
$var wire 16 F debug_r7 [15:0] $end
$var wire 16 G debug_r6 [15:0] $end
$var wire 16 H debug_r5 [15:0] $end
$var wire 16 I debug_r4 [15:0] $end
$var wire 16 J debug_r3 [15:0] $end
$var wire 16 K debug_r2 [15:0] $end
$var wire 16 L debug_r1 [15:0] $end
$var wire 1 M branch_equal $end
$var wire 1 N alu_zero $end
$var wire 1 O alu_src_imm $end
$var wire 16 P alu_result [15:0] $end
$var wire 4 Q alu_op [3:0] $end
$var wire 16 R alu_b [15:0] $end
$var reg 16 S alu_result_reg [15:0] $end
$var reg 16 T instr_reg [15:0] $end
$var reg 16 U mem_data_reg [15:0] $end
$var reg 8 V pc_reg [7:0] $end
$var integer 32 W i [31:0] $end
$scope module u_alu $end
$var wire 16 X b [15:0] $end
$var wire 1 N zero $end
$var wire 4 Y alu_op [3:0] $end
$var wire 16 Z a [15:0] $end
$var reg 16 [ result [15:0] $end
$upscope $end
$scope module u_control_unit $end
$var wire 1 - clk $end
$var wire 4 \ opcode [3:0] $end
$var wire 1 . rst $end
$var reg 4 ] alu_op [3:0] $end
$var reg 1 O alu_src_imm $end
$var reg 1 A ir_write $end
$var reg 1 @ mem_write $end
$var reg 3 ^ next_state [2:0] $end
$var reg 2 _ pc_src [1:0] $end
$var reg 1 = pc_write $end
$var reg 1 < reg_write $end
$var reg 1 ; result_src $end
$var reg 3 ` state [2:0] $end
$upscope $end
$scope module u_register_file $end
$var wire 1 - clk $end
$var wire 16 a debug_r0 [15:0] $end
$var wire 16 b debug_r1 [15:0] $end
$var wire 16 c debug_r2 [15:0] $end
$var wire 16 d debug_r3 [15:0] $end
$var wire 16 e debug_r4 [15:0] $end
$var wire 16 f debug_r5 [15:0] $end
$var wire 16 g debug_r6 [15:0] $end
$var wire 16 h debug_r7 [15:0] $end
$var wire 3 i raddr1 [2:0] $end
$var wire 3 j raddr2 [2:0] $end
$var wire 1 . rst $end
$var wire 3 k waddr [2:0] $end
$var wire 16 l wdata [15:0] $end
$var wire 1 < we $end
$var wire 16 m rdata2 [15:0] $end
$var wire 16 n rdata1 [15:0] $end
$var integer 32 o i [31:0] $end
$upscope $end
$upscope $end
$scope task check16 $end
$var reg 16 p actual [15:0] $end
$var reg 16 q expected [15:0] $end
$var reg 128 r name [127:0] $end
$upscope $end
$upscope $end
$enddefinitions $end
#0
$dumpvars
bx r
bx q
bx p
b1000 o
b0 n
b0 m
b0 l
b0 k
b0 j
b0 i
b0 h
b0 g
b0 f
b0 e
b0 d
b0 c
b0 b
b0 a
b0 `
b0 _
b1 ^
b0 ]
b0 \
b0 [
b0 Z
b0 Y
b0 X
b100000000 W
b0 V
b0 U
b0 T
b0 S
b0 R
b0 Q
b0 P
0O
1N
1M
b0 L
b0 K
b0 J
b0 I
b0 H
b0 G
b0 F
b0 E
b0 D
b0 C
b0 B
1A
0@
b0 ?
b0 >
0=
0<
0;
b0 :
b0 9
b0 8
b0 7
b0 6
b0 5
b0 4
b0 3
b0 2
b0 1
b0 0
b0 /
1.
0-
b0 ,
b0 +
b0 *
b0 )
b0 (
b0 '
b0 &
0%
b0 $
b0 #
b0 "
b0 !
$end
#5000
b1000 o
1-
#10000
0-
#15000
0A
b10 ^
b1011 ?
b1011 \
b1 4
b1 k
b1 E
b101 B
b1 "
b1 5
b1 `
b1011001000000101 $
b1011001000000101 2
b1011001000000101 T
0.
1-
#20000
0-
#25000
0N
b101 P
b101 [
b101 R
b101 X
1O
b100 ^
b10 "
b10 5
b10 `
b1 /
1-
#30000
0-
#35000
1N
b0 P
b0 [
b0 R
b0 X
1=
1<
0O
b0 ^
b101 6
b101 l
b100 "
b100 5
b100 `
b101 S
b10 /
1-
#40000
0-
#45000
1A
0=
0<
b1 ^
b1 #
b1 3
b1 V
b101 ,
b101 L
b101 b
b0 "
b0 5
b0 `
b11 /
1-
#50000
0-
#55000
0A
b10 ^
b10 4
b10 k
b10 E
b111 B
b1 "
b1 5
b1 `
b1011010000000111 $
b1011010000000111 2
b1011010000000111 T
b100 /
1-
#60000
0-
#65000
0N
b111 P
b111 [
b111 R
b111 X
1O
b100 ^
b10 "
b10 5
b10 `
b101 /
1-
#70000
0-
#75000
1N
b0 P
b0 [
b0 R
b0 X
1=
1<
0O
b0 ^
b111 6
b111 l
b100 "
b100 5
b100 `
b111 S
b110 /
1-
#80000
0-
#85000
1A
0=
0<
b1 ^
b10 #
b10 3
b10 V
b111 +
b111 K
b111 c
b0 "
b0 5
b0 `
b111 /
1-
#90000
0-
#95000
b111 R
b111 X
0N
b1100 P
b1100 [
b111 7
b111 m
0M
b101 8
b101 Z
b101 n
b10 9
b10 j
b1 :
b1 i
0A
b10 ^
b1 ?
b1 \
b11 4
b11 k
b11 E
b1 C
b10 D
b10000 B
b1 "
b1 5
b1 `
b1011001010000 $
b1011001010000 2
b1011001010000 T
b1000 /
1-
#100000
0-
#105000
b100 ^
b10 "
b10 5
b10 `
b1001 /
1-
#110000
0-
#115000
1=
1<
b0 ^
b1100 6
b1100 l
b100 "
b100 5
b100 `
b1100 S
b1010 /
1-
#120000
0-
#125000
1A
0=
0<
b1 ^
b11 #
b11 3
b11 V
b1100 *
b1100 J
b1100 d
b0 "
b0 5
b0 `
b1011 /
1-
#130000
0-
#135000
b101 R
b101 X
b101 7
b101 m
b1100 8
b1100 Z
b1100 n
b1 9
b1 j
b111 P
b111 [
b11 :
b11 i
b1 Q
b1 Y
b1 ]
0A
b10 ^
b10 ?
b10 \
b110 4
b110 k
b110 E
b11 C
b1 D
b1000 B
b1 "
b1 5
b1 `
b10110011001000 $
b10110011001000 2
b10110011001000 T
b1100 /
1-
#140000
0-
#145000
b1 Q
b1 Y
b1 ]
b100 ^
b10 "
b10 5
b10 `
b1101 /
1-
#150000
0-
#155000
1=
1<
b1 Q
b1 Y
b1 ]
b0 ^
b111 6
b111 l
b100 "
b100 5
b100 `
b111 S
b1110 /
1-
#160000
0-
#165000
1A
b1 Q
b1 Y
b1 ]
0=
0<
b1 ^
b100 #
b100 3
b100 V
b111 '
b111 G
b111 g
b0 "
b0 5
b0 `
b1111 /
1-
#170000
0-
#175000
b111 R
b111 X
b111 7
b111 m
0M
b101 8
b101 Z
b101 n
b10 9
b10 j
b101 P
b101 [
b1 :
b1 i
b10 Q
b10 Y
b10 ]
0A
b10 ^
b11 ?
b11 \
b111 4
b111 k
b111 E
b1 C
b10 D
b10000 B
b1 "
b1 5
b1 `
b11111001010000 $
b11111001010000 2
b11111001010000 T
b10000 /
1-
#180000
0-
#185000
b10 Q
b10 Y
b10 ]
b100 ^
b10 "
b10 5
b10 `
b10001 /
1-
#190000
0-
#195000
1=
1<
b10 Q
b10 Y
b10 ]
b0 ^
b101 6
b101 l
b100 "
b100 5
b100 `
b101 S
b10010 /
1-
#200000
0-
#205000
1A
b10 Q
b10 Y
b10 ]
0=
0<
b1 ^
b101 #
b101 3
b101 V
b101 &
b101 F
b101 h
b0 "
b0 5
b0 `
b10011 /
1-
#210000
0-
#215000
b111 P
b111 [
b11 Q
b11 Y
b11 ]
0A
b10 ^
b100 ?
b100 \
b1 "
b1 5
b1 `
b100111001010000 $
b100111001010000 2
b100111001010000 T
b10100 /
1-
#220000
0-
#225000
b11 Q
b11 Y
b11 ]
b100 ^
b10 "
b10 5
b10 `
b10101 /
1-
#230000
0-
#235000
1=
1<
b11 Q
b11 Y
b11 ]
b0 ^
b111 6
b111 l
b100 "
b100 5
b100 `
b111 S
b10110 /
1-
#240000
0-
#245000
1A
b11 Q
b11 Y
b11 ]
0=
0<
b1 ^
b110 #
b110 3
b110 V
b111 &
b111 F
b111 h
b0 "
b0 5
b0 `
b10111 /
1-
#250000
0-
#255000
b10 P
b10 [
b100 Q
b100 Y
b100 ]
0A
b10 ^
b101 ?
b101 \
b1 "
b1 5
b1 `
b101111001010000 $
b101111001010000 2
b101111001010000 T
b11000 /
1-
#260000
0-
#265000
b100 Q
b100 Y
b100 ]
b100 ^
b10 "
b10 5
b10 `
b11001 /
1-
#270000
0-
#275000
1=
1<
b100 Q
b100 Y
b100 ]
b0 ^
b10 6
b10 l
b100 "
b100 5
b100 `
b10 S
b11010 /
1-
#280000
0-
#285000
1A
b100 Q
b100 Y
b100 ]
0=
0<
b1 ^
b111 #
b111 3
b111 V
b10 &
b10 F
b10 h
b0 "
b0 5
b0 `
b11011 /
1-
#290000
0-
#295000
b0 R
b0 X
b0 7
b0 m
b0 9
b0 j
b1111111111111010 P
b1111111111111010 [
b101 Q
b101 Y
b101 ]
0A
b10 ^
b110 ?
b110 \
b0 D
b0 B
b1 "
b1 5
b1 `
b110111001000000 $
b110111001000000 2
b110111001000000 T
b11100 /
1-
#300000
0-
#305000
b101 Q
b101 Y
b101 ]
b100 ^
b10 "
b10 5
b10 `
b11101 /
1-
#310000
0-
#315000
1=
1<
b101 Q
b101 Y
b101 ]
b0 ^
b1111111111111010 6
b1111111111111010 l
b100 "
b100 5
b100 `
b1111111111111010 S
b11110 /
1-
#320000
0-
#325000
1A
b101 Q
b101 Y
b101 ]
0=
0<
b1 ^
b1000 #
b1000 3
b1000 V
b1111111111111010 &
b1111111111111010 F
b1111111111111010 h
b0 "
b0 5
b0 `
b11111 /
1-
#330000
0-
#335000
b1100 R
b1100 X
0N
b1100 7
b1100 m
0M
b0 8
b0 Z
b0 n
b1100 P
b1100 [
b11 9
b11 j
b0 :
b0 i
b0 Q
b0 Y
b0 ]
0A
b10 ^
b1000 ?
b1000 \
b11 4
b11 k
b11 E
b0 C
b1 D
b1010 B
b1 "
b1 5
b1 `
b1000011000001010 $
b1000011000001010 2
b1000011000001010 T
b100000 /
1-
#340000
0-
#345000
b1010 P
b1010 [
b1010 R
b1010 X
1O
b11 ^
b10 "
b10 5
b10 `
b100001 /
1-
#350000
0-
#355000
b1100 P
b1100 [
b1100 R
b1100 X
1=
1@
0O
b0 ^
b1010 6
b1010 l
b11 "
b11 5
b11 `
b1010 S
b100010 /
1-
#360000
0-
#365000
1A
0=
0@
b1 ^
b1001 #
b1001 3
b1001 V
b0 "
b0 5
b0 `
b100011 /
1-
#370000
0-
#375000
b101 P
b101 [
b101 R
b101 X
b101 7
b101 m
b1 9
b1 j
0A
b10 ^
b111 ?
b111 \
b100 4
b100 k
b100 E
b1 "
b1 5
b1 `
b111100000001010 $
b111100000001010 2
b111100000001010 T
b100100 /
1-
#380000
0-
#385000
b1010 P
b1010 [
b1010 R
b1010 X
1O
b11 ^
b10 "
b10 5
b10 `
b100101 /
1-
#390000
0-
#395000
b101 P
b101 [
b101 R
b101 X
0O
b100 ^
b11 "
b11 5
b11 `
b100110 /
1-
#400000
0-
#405000
b1100 6
b1100 l
1=
1<
1;
b0 ^
b1100 U
b100 "
b100 5
b100 `
b100111 /
1-
#410000
0-
#415000
b1010 6
b1010 l
1A
0;
0=
0<
b1 ^
b0 "
b0 5
b0 `
b1100 )
b1100 I
b1100 e
b1010 #
b1010 3
b1010 V
b101000 /
1-
#420000
0-
#425000
b1100 R
b1100 X
b11000 P
b11000 [
1M
b1100 7
b1100 m
b1100 8
b1100 Z
b1100 n
b100 9
b100 j
b11 :
b11 i
b1010 ?
b1010 \
b11 4
b11 k
b11 E
b100 C
b0 D
b10 B
0A
b10 ^
b1010011100000010 $
b1010011100000010 2
b1010011100000010 T
b1 "
b1 5
b1 `
b101001 /
1-
#430000
0-
#435000
b1 >
b1 _
1=
b0 ^
b10 "
b10 5
b10 `
b101010 /
1-
#440000
0-
#445000
b11000 6
b11000 l
1A
b0 >
b0 _
0=
b1 ^
b1100 #
b1100 3
b1100 V
b11000 S
b0 "
b0 5
b0 `
b101011 /
1-
#450000
0-
#455000
b101 R
b101 X
b101 P
b101 [
b101 7
b101 m
0M
b0 8
b0 Z
b0 n
b1 9
b1 j
b0 :
b0 i
0A
b10 ^
b1001 ?
b1001 \
b0 4
b0 k
b0 E
b0 C
b1 D
b1110 B
b1 "
b1 5
b1 `
b1001000000001110 $
b1001000000001110 2
b1001000000001110 T
b101100 /
1-
#460000
0-
#465000
b10 >
b10 _
1=
b0 ^
b10 "
b10 5
b10 `
b101101 /
1-
#470000
0-
#475000
1A
b0 >
b0 _
0=
b1 ^
b101 6
b101 l
b0 "
b0 5
b0 `
b1110 #
b1110 3
b1110 V
b101 S
b101110 /
1-
#480000
0-
#485000
1N
b0 P
b0 [
b0 R
b0 X
1M
b0 7
b0 m
b0 9
b0 j
b1111 ?
b1111 \
b0 D
b0 B
0A
b101 ^
b1111000000000000 $
b1111000000000000 2
b1111000000000000 T
b1 "
b1 5
b1 `
b101111 /
1-
#490000
0-
#495000
1%
b101 "
b101 5
b101 `
b110000 /
1-
#500000
0-
#505000
b1100 q
b1100 p
b1001101010001010100110101011011001100010011000001011101 r
b110001 /
1-
